Workbook

Sheet Sheet1
B1: Topic | C1: Count | D1: Name | E1: Representation | F1: Representative_Docs | G1: GPT Label | H1: Better Label? | I1: Category (0 - Background, 1 - Oon before, 2 - Trigger, 3 - Oon after) | J1: Remarks
A2: 0 | B2: 1 | C2: 3225 | D2: 1_mom back_want mom_mom mom_mum | E2: ['mom back', 'want mom', 'mom mom', 'mum', 'love mom', 'relationship mom', 'miss', 'mom always', 'mom want', 'like mom'] | F2: ['I just want my mom back.', 'I want my mom back.', 'I just want my mom back.', 'I just want my mom back.', 'Seriously I want my mom back.'] | G2: Desire for Reconnection with Mother | J2: Narr's needs
A3: 1 | B3: 3 | C3: 2615 | D3: 3_dad dad_love dad_dad always_like dad | E3: ['dad dad', 'love dad', 'dad always', 'like dad', 'miss', 'stepdad', 'know dad', 'dad would', 'dad never', 'step dad'] | F3: ['My dad was always easier.', 'My dad and I have always had a rocky relationship.', 'I love my dad but this is tough to say the least.', 'Despite everything, I love my dad and can‚Äôt help but mourn the childhood I spent with him.', 'I love my dad a lot.'] | G3: Strained Father-Child Relationships Due to QAnon | I3: 3-Oon after-Social
A4: 2 | B4: 4 | C4: 2572 | D4: 4_text_screamed_mad_hung | E4: ['text', 'screamed', 'mad', 'hung', 'argue', 'texted', 'answer', 'stop talking', 'want talk', 'upset'] | F4: ['He asks a lot of questions and I just try to answer them or look them up with him.', 'He started screaming at me, I told him not to raise his fucking voice at me while I‚Äôm trying to have a convo with him and hung up.', 'I was hyperventilating and crying uncontrollably and he interpreted it as me trying to scare him like I was mad or something so he just yelled louder until he left eventually.', 'He‚Äôll discuss it, but he gets pretty upset if you actually bring up good points.', "He knows I don't want to hear it, but he likes making me mad."] | G4: Family Conflict Over QAnon Beliefs | H4: Q's Hostile Behavior towards others | I4: 3-Oon after-Behavior/action
A5: 3 | B5: 5 | C5: 1981 | D5: 5_text_argue_spoken_want talk | E5: ['text', 'argue', 'spoken', 'want talk', 'hung', 'texting', 'answer', 'thanked', 'talk anymore', 'disagree'] | F5: ["I haven't spoken to her since then and it's been about a month.", 'She just want to agree to disagree, I want to discuss the matter, understand her reasoning... so in the end we just agree to disagree.', "Who's going to argue with her?", 'I have yet to text her back.', "I didn't see the text so she called."] | G5: Family Communication Breakdown Due to QAnon Beliefs | I5: 3-Oon after-Behavior/action
A6: 4 | B6: 13 | C6: 1121 | D6: 13_doctor_doctors_cancer_hospital | E6: ['doctor', 'doctors', 'cancer', 'hospital', 'medical', 'meds', 'medicine', 'medication', 'cure', 'treatment'] | F6: ['(Give her cancer or something).', 'Not to mention SHE IS A DOCTOR!!!', 'I urged her to get to her doctor.', 'You cannot just look at her and say she‚Äôs not a doctor.', "She is the hospital right now, and I don't how long she's had the cancer yet."] | G6: Family Impact of Medical Misinformation in QAnon Context | H6: Distrust in doctors? | I6: 3-Oon after-Behavior/action
A7: 5 | B7: 20 | C7: 850 | D7: 20_oxygen_hospital_doctor_doctors | E7: ['oxygen', 'hospital', 'doctor', 'doctors', 'medical', 'heart attack', 'diabetes', 'medication', 'cancer', 'failure'] | F7: ['He is over 70 and has diabetes, high blood pressure, and congestive heart failure.', 'His wife has been sick and is now in hospital.', 'And after evaluating him they decided to bring him to a mental hospital.', 'After getting out of the hospital.. he was not the same.', 'His blood oxygen when he made it to the ER was 76.'] | G7: Health and Medical Issues Related to QAnon Beliefs | H7: Related to QAnon Beliefs | I7: 0-Background-Health
A8: 6 | B8: 29 | C8: 630 | D8: 29_sisters_siblings_brothers_older | E8: ['sisters', 'siblings', 'brothers', 'older', 'little sister', 'older sister', 'told brother', 'younger', 'niece', 'younger sister'] | F8: ['Two of my older sisters feel the same way more or less.', "My older sister has begun to just ignore my mom, while my little sister (who has autism) is very upset that she can't make my mom understand she's being ridiculous.", 'i talked to my older sister about this too.', 'We were closer sisters than me and my blood sister.', 'She is mad at me and my 2 sisters.'] | G8: Family Dynamics and QAnon Influence on Sibling Relationships | H8: QAnon Influence on Family Dynamics (Sibling Relationships) | I8: 3-Oon after-Impact to others
A9: 7 | B9: 31 | C9: 618 | D9: 31_drops_believer_related_full blown | E9: ['drops', 'believer', 'related', 'full blown', 'blown', 'er', 'followers', 'anonymous', 'believers', 'discovered'] | F9: ['He is a stout Q believer.', "I look through his posts, he's full blown Q guy, Trump is the savior, the whole thing.", 'He pretty quickly became a full blown q convert and stopped going into work more and more often so he could spend more time watching youtube and talking to other fellow believers.', 'Sorry for the rant..... anyway......\n\nNot only was everyone I was watching talking about "Q Drops"...but they were also all becoming..............extremely fond of Trump.', 'he calls Q drops and the videos from top Q believers on youtube the "new Bible" and tells me to throw my copies of the "old" one away.'] | G9: QAnon Belief and Influence on Personal Lives | H9: Full-blown stage into Q?
A10: 8 | B10: 34 | C10: 569 | D10: 34_daughter_rest family_parent_side family | E10: ['daughter', 'rest family', 'parent', 'side family', 'family really', 'kid', 'grandparent', 'people family', 'son', 'sees'] | F10: ['But it kills me knowing that the rest of my family has to deal with him.', 'The rest of my family wouldn‚Äôt engage the subject at all with him.', "i don't know what to do or how to be his daughter anymore.", "I'm his daughter, his only child.", 'What do I say to demonstrate that he should put his daughter first, above all of this crap??'] | G10: Family Struggles with QAnon Beliefs | H10: QAnon Influence on Family Dynamics | I10: 3-Oon after-Impact to others
A11: 9 | B11: 35 | C11: 556 | D11: 35_boyfriend_hes_cheated_divorce | E11: ['boyfriend', 'hes', 'cheated', 'divorce', 'dare', 'agrees', 'dating', 'lets', 'ex', 'goes along'] | F11: ["It started with him threatening to dox and expose her, but then it moved to threatening to harm her, her boyfriend and even her boyfriend's cat if she didn't come back to him.", 'I don‚Äôt think he agrees with her beliefs but he just kind of lets it happen.', "Then she met her boyfriend, let's call him Dave.", '(The TL;DR of that is she had a boyfriend but cheated on that guy with my friend, but I again veer into other topics).', 'Her base for divorce was \'Hes not awake, hes part of the cabal, hes keeping secrets from me, hes gay"....'] | G11: Relationship Strain Due to QAnon Beliefs | H11: ??? | I11: 0-Background-Partner
A12: 10 | B12: 39 | C12: 523 | D12: 39_insanity_crazy one_madness_sane | E12: ['insanity', 'crazy one', 'madness', 'sane', 'sanity', 'craziness', 'like crazy', 'think crazy', 'going crazy', 'going insane'] | F12: ['I feel like I‚Äôm the crazy one.', "I don't think I have it in me to deal with any more of this insanity.", 'The man lost *everything* to this insanity.', "I'm so sick of the insanity.", 'When does this insanity end?'] | G12: Family Struggles with QAnon-Induced Insanity | H12: Family Struggles
A13: 11 | B13: 40 | C13: 523 | D13: 40_missing_saving children_protect_saving | E13: ['missing', 'saving children', 'protect', 'saving', 'safety', 'kid', 'save children', 'abuse', 'kids want', 'child abuse'] | F13: ['The estrangements were painful for these parents and in an attempt to help them process what was happening, the essay author noticed a trend of ‚Äúmissing missing reasons.‚Äù TL;DR these estranged parents almost uniformly were unable to say why they had been cut off by their adult children.', 'I am so frustrated with this "missing children" crap.', 'In many countries, statistics on missing children are not even available; and, unfortunately, even available statistics may be inaccurate due to: under-reporting/under-recognition; inflation; incorrect database entry of case information; and deletion of records once a case is closed.‚Äù \n\nand also\n\n ‚Äú250,000 children are reported missing every year in the EU, 1 child every 2 minutes‚Äù\n\ni know that the vast majority of these reported cases are custody disputes between estranged parents, but he is completely sold that these kids are legitimately abducted and trafficked, despite that being an absolutely insane number, and wouldn‚Äôt that constitute the biggest news story of our times!?', 'You thought you were saving children?', 'And where the hell are all the missing migrant children?!?!?!?!?!'] | G13: Concerns about Missing and Abducted Children | H13: Q's Belief "Save the Children" | I13: 3-Oon after-Belief
A14: 12 | B14: 42 | C14: 496 | D14: 42_relationships_strained_end relationship_repair | E14: ['relationships', 'strained', 'end relationship', 'repair', 'good relationship', 'strain relationship', 'strain', 'surface level', 'time together', 'complicated'] | F14: ['Things have been strained between the two of us since.', "In other words, it's time for me to triage my relationships.", 'I had been in several dysfunctional relationships but this was the worst.', 'Sometimes those relationships can be mended; sometimes they can‚Äôt be.', 'Suffice it to say the relationships are very strained.'] | G14: Strained Relationships Due to QAnon Involvement | I14: 3-Oon after-Social
A15: 13 | B15: 43 | C15: 493 | D15: 43_black_racist_white_racism | E15: ['black', 'racist', 'white', 'racism', 'black people', 'white people', 'race', 'brown', 'supremacy', 'color'] | F15: ['One of the things growing up that we both really struggled with was race and how having a white mother and black father was being too white for the black kids and too black for the white kids.', 'My boyfriend is black, his friend is white, and I am also white.', 'I am a black woman and my husband is a white man from the Midwest.', 'Im in a multiracial family, and often grapple with the fact that my father can be so racist when he has a black son and wife.', 'As far as racism goes everyone in the world is racist in some way.'] | G15: Interracial Relationships and Racism Experiences | I15: 0-Background-Race
A16: 14 | B16: 44 | C16: 484 | D16: 44_conversations_spoken_spoken since_communication | E16: ['conversations', 'spoken', 'spoken since', 'communication', 'end conversation', 'want talk', 'talk phone', 'talk anything', 'conversation went', 'small talk'] | F16: ['We‚Äôve had many of these conversations.', 'We were able to have real conversations.', 'Any conversations we have can be kept confidential for now.', 'We do not talk often so it never comes up in our conversations.', 'Our conversations were only about this.'] | G16: Communication Challenges in Conversations | H16: ??? | I16: ???
A17: 15 | B17: 45 | C17: 474 | D17: 45_ivermectin_horse_cure_paste | E17: ['ivermectin', 'horse', 'cure', 'paste', 'doctor', 'treat', 'doctors', 'medicine', 'doses', 'ordered'] | F17: ['and they with their buckets of ivermectin dgaf then, so why does it matter now?).', 'I have a question about ivermectin.', 'I said, "No, I won\'t be taking ivermectin.', "Ivermectin and hydroxychloroquine aren't working.", 'What effectiveness had ivermectin had anyway?'] | G17: Ivermectin Use and Skepticism in Treating Illness | I17: 3-Oon after-Belief
A18: 16 | B18: 50 | C18: 445 | D18: 50_currency_gold_silver_crypto | E18: ['currency', 'gold', 'silver', 'crypto', 'scam', 'debt', 'bank', 'dollar', 'banks', 'worthless'] | F18: ["He's been slowly funneling out our money to crypto currency that I don't have access to.", 'Thankfully he just bought gold and silver with it though.', 'My mom is spending hers and my dads life savings on crypto currency and also buying all sorts of worthless currency from EBay (Zimbabwe, Iraqi, Venezuelan currency).', 'Then somehow it turns into how we aren‚Äôt aware of what‚Äôs happening in this country and how currency is about to change to gold and silver and demanded that tomorrow he is going to buy gold!', 'He wants to put all our money into gold/silver purchases.'] | G18: Financial Decisions Influenced by Conspiracy Beliefs | I18: 3-Oon after-Behavior/action
A19: 17 | B19: 51 | C19: 443 | D19: 51_christmas_thanksgiving_holidays_holiday | E19: ['christmas', 'thanksgiving', 'holidays', 'holiday', 'celebrate', 'easter', 'eve', 'xmas', 'season', 'home christmas'] | F19: ['Christmas is just going to be different through and through.', 'I‚Äôm honestly thinking about skipping Christmas.', 'Most of my family spent Christmas day together.', 'Our Christmas traditions won‚Äôt be the same.', 'We usually spend Thanksgiving and Christmas with my family but not this year.'] | G19: Family Holiday Gatherings Affected by QAnon | I19: 3-Oon after-Impact to others
A20: 18 | B20: 52 | C20: 440 | D20: 52_step dad_told dad_step_even dad | E20: ['step dad', 'told dad', 'step', 'even dad', 'divorce', 'dad said', 'dad would', 'dad told', 'dad thinks', 'divorced'] | F20: ['She has threatened to divorce my dad after nearly 20 years of marriage because he expressed concern in her habits and behavior.', '(It at least makes me feel better that even my dad needed to see her freak out like this to realize how deep the manipulation went, and he was married to her for over 20 years before they divorced when I was in high school.', "she also said she couldnt text about it, could only talk on the phone wtf\n\ni texted my step dad saying i didn't appreciate her threatening me and to knock it off!", 'I told my dad (her son) that she hasn‚Äôt had an original thought for a long time because my step-grandpa won‚Äôt let her.', 'I am afraid she will lose my step dad.'] | G20: Family Strain Due to QAnon Beliefs | H20: (Stepdad) / manipulation | I20: 3-Oon after-Behavior/action
A21: 19 | B21: 53 | C21: 437 | D21: 53_weed_drugs_mental health_bipolar | E21: ['weed', 'drugs', 'mental health', 'bipolar', 'depression', 'addict', 'drug', 'drinking', 'schizophrenia', 'alcohol'] | F21: ["This is the same man that grew weed in our house growing up because then Government can't tell him what to do.", 'Keep in mind this person was outgoing and rebellious as a kid but growing up and after making poor decisions, from smoking weed to then more hard drugs such as meth, they‚Äôve became very different.', 'He has very strong anxiety and smokes a lot of weed.', 'Dmt, shrooms, weed, etc, should be stopped.', 'Also, he was not just on weed.'] | G21: Substance Use and Mental Health Issues | I21: 0-Background-Substance Use
A22: 20 | B22: 54 | C22: 427 | D22: 54_want kids_whole family_rest family_grandchild | E22: ['want kids', 'whole family', 'rest family', 'grandchild', 'son', 'extended family', 'see kids', 'family members', 'much family', 'contact family'] | F22: ["I swear she quotes all of the speaker's she sees I agreed with her and said I didn't want my kids to grow up with that outlook.", 'When she asked what kind of things I said things like who you want your kids to go to and medical things like a DNR.', 'She is in deep and says her whole family is as well.', "I've tried so hard to have a relationship with her for the sake of my kid, her own grandchild, because I know how much she loves him.", "She's estranged to the whole family, and I'm basically the only link I have from her to the rest of the family."] | G22: Family Estrangement Due to QAnon Beliefs | I22: 3-Oon after-Impact to others
A23: 21 | B23: 55 | C23: 412 | D23: 55_therapy_therapist_counseling_therapists | E23: ['therapy', 'therapist', 'counseling', 'therapists', 'couples', 'counselor', 'appointment', 'session', 'sessions', 'insurance'] | F23: ['And I‚Äôm still in therapy.', 'I have done the most therapy(by far).', 'I‚Äôm working on it with therapy.', "I've been through years of therapy.", 'I have recently been going to therapy to deal with these issues.'] | G23: Coping with QAnon-Related Family Strain through Therapy | I23: 3-Oon after-Impact to narr
A24: 22 | B24: 56 | C24: 405 | D24: 56_arguments_arguing_argue_argument | E24: ['arguments', 'arguing', 'argue', 'argument', 'debate', 'disagree', 'agree disagree', 'civil', 'debating', 'argued'] | F24: ["These weren't the only arguments we had about this, there was more.", "We've had these arguments already.", "We've never gotten into more arguments.", 'YOU TAKE ALL MY ARGUMENTS!', "Since then we've been fine, no arguments or anything at all."] | G24: Family Disputes Over QAnon Beliefs | H24: Family Arguments Over QAnon Beliefs | I24: 3-Oon after-Behavior/action
A25: 23 | B25: 58 | C25: 396 | D25: 58_mum_help mom_told mom_mom says | E25: ['mum', 'help mom', 'told mom', 'mom says', 'mom goes', 'get mom', 'agrees', 'mom mom', 'mom like', 'mom always'] | F25: ['Sometimes I just think about if his need for a car/help for his mom wasn‚Äôt in the picture, would he have stretched that timeframe of not wanting to be around me further?', 'I told my mom and she said he refuses to apologize since he was "tired when he said it".', 'We got passed him not wanting to see me because I am ‚Äúshedding‚Äù but a part of me believes that he only let me back in (being physically around him) because he needed help with his elderly mother (and not having car to help with his mom).', 'I am trying to help him and my mom to get into counseling for resolving there past conflict and become more open to one another.', 'He needed help with mom.'] | G25: Family Dynamics and Support Involving Mom | H25: ??? | I25: ???
A26: 24 | B26: 59 | C26: 394 | D26: 59_miss_love much_still love_feel bad | E26: ['miss', 'love much', 'still love', 'feel bad', 'senses', 'loves', 'want relationship', 'person used', 'come back', 'get back'] | F26: ['I want him to miss me too.', 'I miss him more than anything.', 'I just miss him so very, very much!', 'I miss him so much.', 'I just miss him and wish it wasn‚Äôt like this.'] | G26: Missing Loved Ones Due to QAnon Involvement | I26: 3-Oon after-Impact to narr
A27: 25 | B27: 60 | C27: 394 | D27: 60_cried_cry_crying_tears | E27: ['cried', 'cry', 'crying', 'tears', 'scream', 'sobbing', 'laugh', 'void', 'eyes', 'broke'] | F27: ['I cried because of how happy I was.', 'I cried so much already.', 'Maybe I cried all I could that day in the barn.', 'I cried, I was angry, I had so much sorrow, and I grieved.', 'I have cried so many tears and am on anti depressants to help me out.'] | G27: Emotional Distress and Coping | I27: 3-Oon after-Impact to narr
A28: 26 | B28: 64 | C28: 363 | D28: 64_older brother_brothers_older_younger brother | E28: ['older brother', 'brothers', 'older', 'younger brother', 'brother said', 'like brother', 'little brother', 'younger', 'brother told', 'lose'] | F28: ['My older brother has always walked on water in my eyes.', "I MISS MY OLDER BROTHER WHO I WISHED TO BE AS COOL AS GROWING UP BUT NOW I DON'T EVEN RECOGNIZE YOU.", 'My brothers are the same.', 'Both of my brothers have done this, it‚Äôs my turn.', 'My older brother was so special to us (lost him \\~7 years ago).'] | G28: Family Strain Due to QAnon Beliefs | H28: (Narrator-oon) Relationship with Brother? | I28: 0-Background-Relationship with narr
A29: 27 | B29: 66 | C29: 353 | D29: 66_twitter_facebook_fb_banned | E29: ['twitter', 'facebook', 'fb', 'banned', 'social media', 'account', 'https twitter', 'https twitter com', 'twitter com', 'instagram'] | F29: ['The best way to keep up on happenings is with these Twitter accounts:\n\n&#x200B;\n\n[https://twitter.com/fr\\_brennan](https://twitter.com/fr_brennan)\n\n[https://twitter.com/Kirtaner](https://twitter.com/Kirtaner)\n\n[https://twitter.com/AJVicens](https://twitter.com/AJVicens)\n\n[https://twitter.com/alibreland](https://twitter.com/alibreland)\n\n[https://twitter.com/AmericanHacker](https://twitter.com/AmericanHacker)\n\n[https://twitter.com/FoucaultMotoko](https://twitter.com/FoucaultMotoko)', 'He‚Äôs more active on twitter than fb.', "I looked down at my phone for something and saw the announcement that Trump's twitter account had been banned.", 'His Twitter account got banned a day before trump‚Äôs did.', 'I ask him to give up twitter (for a few days) and he can‚Äôt do that.'] | G29: Social Media and QAnon Involvement | I29: 2-Trigger-Social Media
A30: 28 | B30: 69 | C30: 345 | D30: 69_boundaries_bring back_like lost_want back | E30: ['boundaries', 'bring back', 'like lost', 'want back', 'breaks heart', 'feel like lost', 'want lose', 'breaks', 'get back', 'love much'] | F30: ['I feel like I lost her.', 'I feel like I lost her.', "I feel like she's lost to me.", 'he backed me up in my boundaries because he also has those boundaries with her, And is definitely the only reason why she is adhering to those boundaries right now.', 'She won‚Äôt adhere to my boundaries.'] | G30: Family Strain Due to QAnon Beliefs | I30: 3-Oon after-Impact to narr | J30: Narr's feeling
A31: 30 | B31: 73 | C31: 329 | D31: 73_youtube_algorithm_podcast_youtube videos | E31: ['youtube', 'algorithm', 'podcast', 'youtube videos', 'channel', 'algorithms', 'youtube com', 'youtube video', 'https', 'videos articles'] | F31: [' \n\nHello everyone,\n\nmy Name is Adrian and I am a journalist, working for the german television broadcast SPIEGEL TV MAGAZIN (Our YT-Channel: [https://www.youtube.com/user/spiegeltv](https://www.youtube.com/user/spiegeltv)).', 'Another interesting video I found on youtube is this one: [https://www.youtube.com/watch?v=NPHwO\\_sVSAQ](https://www.youtube.com/watch?v=NPHwO_sVSAQ).', 'I didn‚Äôt click on the YouTube video he sent because I didn‚Äôt want the algorithm to think I was interested in that.', 'But a lot comes from YouTube.', 'His youtube algorithm is nothing but this stuff.'] | G31: Impact of YouTube Algorithms on QAnon Content Consumption | I31: 2-Trigger-Social Media
A32: 31 | B32: 74 | C32: 327 | D32: 74_grief_grieving_mourning_grieve | E32: ['grief', 'grieving', 'mourning', 'grieve', 'betrayed', 'loss', 'like mourning', 'still alive', 'mourn', 'alive'] | F32: ['I felt the grief again.', "It feels like I'm grieving for someone who is still alive.", 'It feels like grieving a loss.', 'We are literally grieving the loss of our loved ones while they are still alive.', "I've honestly felt grief at the loss."] | G32: Grieving the Living | I32: 3-Oon after-Impact to narr
A33: 32 | B33: 78 | C33: 311 | D33: 78_pandemic_pandemic started_pandemic hit_since pandemic | E33: ['pandemic', 'pandemic started', 'pandemic hit', 'since pandemic', 'start pandemic', 'hit', 'pandemic really', 'pandemic began', 'beginning pandemic', 'got worse'] | F33: ["I'm frigging sick of this pandemic.", 'I hate what this pandemic has done to my kids‚Äô lives.', 'And then the pandemic happened.', "With the pandemic, it's been worse.", 'All well before the pandemic.'] | G33: Impact of the Pandemic on Personal Lives | I33: 2-Trigger-Pandemic
A34: 33 | B34: 81 | C34: 307 | D34: 81_baby_pregnant_pregnancy_first child | E34: ['baby', 'pregnant', 'pregnancy', 'first child', 'newborn', 'birth', 'born', 'expecting', 'grandchild', 'daughter'] | F34: ['How does anyone do this to their baby?!', 'We are having a baby soon.', "I kissed my baby's forehead and left.", 'I was just worried about my baby.', "Or, let's make love and make a baby."] | G34: Family and Pregnancy Concerns in QAnon Context | I34: 0-Background-Family
A35: 34 | B35: 83 | C35: 303 | D35: 83_retirement_lost job_fired_business | E35: ['retirement', 'lost job', 'fired', 'business', 'company', 'works', 'get job', 'retired', 'jobs', 'unemployed'] | F35: ['He hasnt lost his job yet, but it may happen.', 'Once he got to the U.S he worked a few odd jobs and started his own business.', 'They are maxed again and he is running out of retirement.', "He's a man nearing retirement age with a family.", 'He, the fucker, who‚Äôs close to retirement age anyway.'] | G35: Impact of QAnon on Employment and Retirement | H35: Impact of QAnon on | I35: 0-Background-Job
A36: 35 | B36: 86 | C36: 295 | D36: 86_sources_article_articles_source | E36: ['sources', 'article', 'articles', 'source', 'credible', 'reliable', 'proof', 'send', 'fake news', 'google'] | F36: ["I've sent her so many sources counteracting her and my uncle's claims.", 'I easily found multiple articles for each of her sources that debunked the information claimed and showed why these sources were not credible.', 'I asked her what sources she would trust.', 'I ask for sources and there is never any real source to back up the claims, but I "have to understand, she is getting this information from credible sources."', 'She won\'t listen to any fact, only these "sources".'] | G36: Credibility of Information Sources | H36: Q's unsourced belief? | I36: 3-Oon after-Behavior/action
A37: 36 | B37: 91 | C37: 279 | D37: 91_gates_bill gates_bill_5g | E37: ['gates', 'bill gates', 'bill', '5g', 'microchips', 'microchip', 'dna', 'vaccines', 'kill', 'population'] | F37: ['* Bill Gates - eugenics, decreasing the population, and vaccines\n* Globalism/NWO - George Soros, the Rockefellers, Jeff Bezos, Bill Gates, Klaus Schwabb, etc.', "And it was Bill Gates' company.", 'And of course the 5G, Covid, and Bill Gates conspiracies make sense to them.', 'Bill Gates is trying to implant microchips.', "I honestly still don't understand the Bill Gates thing."] | G37: Bill Gates and Conspiracy Theories | I37: 3-Oon after-Belief
A38: 37 | B38: 92 | C38: 276 | D38: 92_red_texas_florida_area | E38: ['red', 'texas', 'florida', 'area', 'rural', 'town', 'county', 'city', 'states', 'blue'] | F38: ['We live in a red state.', "We're also in a red state.", 'Still, he is deep in a red state.', 'We are from a very small rural red town.', 'I live in a very red area.'] | G38: Impact of QAnon in Conservative Rural Areas | H38: Demographics (red state) | I38: 0-Background-Political region
A39: 38 | B39: 99 | C39: 258 | D39: 99_racist_white_black_black people | E39: ['racist', 'white', 'black', 'black people', 'racism', 'race', 'racial', 'white supremacists', 'supremacists', 'white people'] | F39: ['He told me not to be racist.', 'That Trump is not now, nor has he ever been racist.', 'He is racist and he knows it.', 'It made him more racist.', 'He‚Äôs been doing this and making racist stereotypes.'] | G39: Racism and Racial Attitudes in QAnon Narratives | I39: 3-Oon after-Behavior/action
A40: 39 | B40: 100 | C40: 254 | D40: 100_anxiety_ocd_panic_panic attacks | E40: ['anxiety', 'ocd', 'panic', 'panic attacks', 'panic attack', 'attacks', 'attack', 'disorder', 'roof', 'depression'] | F40: ['Saying it was an anxiety attack.', 'Anxiety and panic attacks can mimic serious health issues which is compounding my fear.', 'I have an anxiety disorder and ocd.', 'I kept having panic attacks and my anxiety was so bad.', "Which I still haven't gotten myself to do because of the anxiety around it."] | G40: Anxiety and Panic Disorders | I40: 3-Oon after-Impact to narr
A41: 40 | B41: 102 | C41: 251 | D41: 102_stolen_election stolen_fraud_election fraud | E41: ['stolen', 'election stolen', 'fraud', 'election fraud', 'rigged', 'voter fraud', 'voter', 'election rigged', 'stolen election', 'believes election'] | F41: ['He said the election was stolen.', 'Thinks the election was stolen.', 'He thinks their election was stolen and is always angry.', 'They now believe the election was stolen.', 'They dont believe the election was stolen.'] | G41: Belief in Election Fraud | I41: 3-Oon after-Belief
A42: 42 | B42: 106 | C42: 247 | D42: 106_safety_dangerous_protect_risk | E42: ['safety', 'dangerous', 'protect', 'risk', 'careful', 'danger', 'bubble', 'precautions', 'feel safe', 'high risk'] | F42: ['and why it is so dangerous?', 'They‚Äôre crazy but they‚Äôre not dangerous.', 'This had me thinking about how dangerous this really is.', 'That said, risk was low but I have to be careful because we have at-risk people in our bubble.', 'I am not worried for my safety AT ALL.'] | G42: Concerns About Safety and Risk | I42: 3-Oon after-Impact to others
A43: 43 | B43: 107 | C43: 245 | D43: 107_moving_housing_rent_afford | E43: ['moving', 'housing', 'rent', 'afford', 'apartment', 'financially', 'next year', 'option', 'income', 'financially dependent'] | F43: ["As for moving out, I'm trying.", 'I am honestly thinking of moving out.', 'I am contemplating moving out.', "I can't even afford subsidized housing at this point in time because rent is just crazy (as it is getting to be everywhere it seems).", 'I can‚Äôt really afford to add more housing expenses.'] | G43: Financial Struggles with Housing and Moving Out | I43: 3-Oon after-Impact to narr
A44: 44 | B44: 109 | C44: 242 | D44: 109_leaving_walk away_walk_want leave | E44: ['leaving', 'walk away', 'walk', 'want leave', 'like leave', 'ride', 'need get', 'get feel', 'might make', 'exit'] | F44: ['How do you know when the only thing you can/should do is walk away?', 'When do I just walk away?', 'I decided we were leaving right then.', 'Do I need to give a reason why I‚Äôm leaving you behind?', "I'm ok with leaving if it doesn't work."] | G44: Leaving QAnon Involvement | H44: Narrator leaving Q people | I44: 3-Oon after-Social
A45: 45 | B45: 110 | C45: 239 | D45: 110_storm_fires_weather_fire | E45: ['storm', 'fires', 'weather', 'fire', 'snow', 'smoke', 'warm', 'burning', 'fuel', 'burn'] | F45: ['So...what exactly is The Storm, then?', 'But what happens after "the storm"?', 'And the fires in Hawaii?', 'Ok, I didn‚Äôt actually storm.', 'Do I just weather the storm?'] | G45: QAnon Conspiracy and Natural Disasters | I45: 3-Oon after-Belief
A46: 46 | B46: 111 | C46: 238 | D46: 111_doctors_beds_medical_med beds | E46: ['doctors', 'beds', 'medical', 'med beds', 'med', 'medicine', 'doctor', 'pharma', 'big pharma', 'medbeds'] | F46: ['I have seen doctors misdiagnose.', 'As they have made me petrified of doctors.', 'They put us off saying they needed to talk to their doctors.', "But the doctors haven't found a cause?", 'Most are *doctorates*, not medical doctors.'] | G46: Distrust in Medical Professionals | I46: 3-Oon after-Belief
A47: 47 | B47: 114 | C47: 226 | D47: 114_siblings_cousin_cousins_sibling | E47: ['siblings', 'cousin', 'cousins', 'sibling', 'aunts', 'uncle', 'older', 'aunt', 'aunt uncle', 'brothers'] | F47: ['I have many other siblings.', 'And I‚Äôm their only child, no siblings.', "Me and my siblings don't know what to do.", 'I just sorry for my siblings', 'My cousins were like siblings.'] | G47: Family Relationships and QAnon Impact | H47: [Oon-Narrator) Relationship - Siblings | I47: 0-Background-Relationship with narr
A48: 48 | B48: 115 | C48: 220 | D48: 115_trump supporter_supporter_politics_2016 | E48: ['trump supporter', 'supporter', 'politics', '2016', 'trump supporters', 'dad said', 'supporters', 'trumper', 'since 2016', 'voted'] | F48: ['I live in australia and my dad is a Trump supporter and has been since 2016 since then he had been watching Alex Jones, Fox News and some youtube‚Äôs supporting Trump.', 'My (F32) dad has always been a Trump supporter.', 'My dad is a Trump supporter.', '\n\nMy dad is very much a trump supporter.', 'My dad has been a Trump supporter for a while now.'] | G48: Parental Trump Support Since 2016 | I48: 0-Background-Political leaning
A49: 49 | B49: 117 | C49: 217 | D49: 117_2021_march_date_2016 | E49: ['2021', 'march', 'date', '2016', 'jan', 'january', '6th', 'october', 'february', 'august'] | F49: ['That was in August 2021.', "2021 hasn't been kind to me at all.", 'I cannot find a consecutive 3 days without any quarrel in 2021.', 'Back in the begging of 2021, we were talking about the election, Jan. 6th, etc.', 'but jan 6th on 2021 is what changed me completely for some reason.'] | G49: Impact of 2021 Events on Personal Lives
A50: 50 | B50: 119 | C50: 213 | D50: 119_satanic_satan_satanist_satanists | E50: ['satanic', 'satan', 'satanist', 'satanists', 'worshipping', 'hollywood', 'devil', 'pedophiles', 'panic', 'satanism'] | F50: ['He even posted the other day that everyone who is and voted for Democrats is a Satanic Pedophile.', 'My brother was once just a light Q in 2020 talking about Hollywood Satanic rituals.', '!‚Äù And ‚ÄúWhy the hell do you want to do this satanic major‚Äù.', 'Demons in inanimate objects, satanic music, satanic words, satanic rituals.', 'Believes in satanic paedophile rituals etc.'] | G50: Satanic Panic and QAnon Beliefs | H50: Satanic Perception and QAnon Beliefs | I50: 3-Oon after-Belief
A51: 51 | B51: 121 | C51: 210 | D51: 121_brainwashed_brainwashing_brain washed_washed | E51: ['brainwashed', 'brainwashing', 'brain washed', 'washed', 'brainwash', 'liberal', 'brain', 'leftist', 'believe everything', 'mind control'] | F51: ['You believe I‚Äôm brainwashed and I think The same.', 'It‚Äôs an entire country brainwashed.', 'How brainwashed and lost they are.', 'what if everyone really is brainwashed?', 'My brother is so fucking brainwashed.'] | G51: Family Struggles with Perceived Brainwashing | J51: Narr's feeling
A52: 52 | B52: 122 | C52: 210 | D52: 122_sheep_sheeple_black_brainwashed | E52: ['sheep', 'sheeple', 'black', 'brainwashed', 'wake', 'calling', 'calls', 'called stupid', 'eyes', 'blindly'] | F52: ['So my dad critizes me for my being a sheep.', "Will they tell him that he's stupid, he doesn't understand, he's wrong, he's a sheep, he's an embarrassment?", 'That I was a sheep.', 'He is now left to the sheep.', 'I, once again, am a beta man and sheep.'] | G52: Family Tensions Over "Sheep" Label in QAnon Beliefs | I52: ??? | J52: Oon's perception
A53: 53 | B53: 124 | C53: 208 | D53: 124_nurse_nurses_surgery_nursing | E53: ['nurse', 'nurses', 'surgery', 'nursing', 'doctor', 'doctors', 'er', 'hospital', 'grandma', 'asthma'] | F53: ['My mother is a Nurse Practitioner at a nursing home.', 'Her mother, an actual Nurse.', "I don't want to be a nurse anymore.", '‚ÄúBut mom, you‚Äôre a nurse.', 'The next was a friend I have who is a nurse.'] | G53: Healthcare Professionals and Family Dynamics | I53: ???
A54: 54 | B54: 127 | C54: 205 | D54: 127_guilt_guilty_feel guilty_embarrassed | E54: ['guilt', 'guilty', 'feel guilty', 'embarrassed', 'ashamed', 'embarrassing', 'shame', 'still feel', 'admit', 'guilt trip'] | F54: ['I feel guilty for some reason.', 'I feel plagued by guilt.', 'I don‚Äôt have that guilt anymore.', 'I have so much guilt.', 'You can deal with the self guilt later.'] | G54: Feelings of Guilt and Shame | I54: 3-Oon after-Impact to narr
A55: 55 | B55: 129 | C55: 204 | D55: 129_maga_ultra_movement_die hard | E55: ['maga', 'ultra', 'movement', 'die hard', 'branch', 'im tired', 'cult', 'hate filled', 'surrounded', 'sa'] | F55: ['My husband is MAGA and Q..basically the same thing to me.', 'In the name of MAGA.', 'I can‚Äôt deal with his transformation to a MAGA.', 'Now he is full MAGA.', 'So what about Trump and maga is so different than that?'] | G55: Family Struggles with MAGA/QAnon Beliefs | H55: Family Struggles with | I55: 3-Oon after-Belief
A56: 56 | B56: 132 | C56: 195 | D56: 132_forgive_apology_forgiveness_apologizing | E56: ['forgive', 'apology', 'forgiveness', 'apologizing', 'apologized', 'apologize', 'apologise', 'forget', 'owe', 'know ever'] | F56: ['With all that being said, I forgive you.', '& that‚Äôs okay, I forgive you.', 'I will never forgive him for this.', 'He‚Äôs very remorseful for everything and it‚Äôs taking a while for him to fully forgive himself.', 'He took money from my husband and I cannot forgive that.'] | G56: Family Forgiveness and Resentment | I56: 3-Oon after-Impact to narr | J56: But there're two different sentiments of narr?
A57: 57 | B57: 133 | C57: 192 | D57: 133_journalists_fake news_mainstream_mainstream media | E57: ['journalists', 'fake news', 'mainstream', 'mainstream media', 'news sources', 'bias', 'fake', 'sources', 'outlets', 'journalism'] | F57: ['It\'s all "fake news".... ... ... ... ... ... ... ... really?', 'I understand mainstream media is not perfect and of course they have their own bias they make mistakes they even lie sometimes but atleast I know there mostly credible, studied journalists and don‚Äôt want to ruin reputation.', '"How can you know when you only read "fake news" and the mainstream media and what "they" want you to read" - "because I don\'t.', 'No mainstream media can be trusted?', "Don't listen to the mainstream media."] | G57: Distrust in Mainstream Media | I57: 3-Oon after-Behavior/action
A58: 58 | B58: 134 | C58: 192 | D58: 134_talk anymore_speak anymore_even talk_avoiding | E58: ['talk anymore', 'speak anymore', 'even talk', 'avoiding', 'talk really', 'talk know', 'talk anything', 'interacting', 'really nothing', 'able talk'] | F58: ['I cant talk to any of them anymore.', 'None of them will speak to me anymore.', 'I hardly speak to them anymore.', 'I don‚Äôt speak with them anymore.', "And I can't take being in the same room as them when they talk about it anymore."] | G58: Family Communication Breakdown Due to QAnon | I58: 3-Oon after-Impact to narr
A59: 59 | B59: 135 | C59: 191 | D59: 135_fox_tucker_fox news_carlson | E59: ['fox', 'tucker', 'fox news', 'carlson', 'tucker carlson', 'alex jones', 'alex', 'jones', 'newsmax', 'watches'] | F59: ["The only thing she even watches is Fox News and she's a HUGE fan of Tucker Carlson, but I imagine she follows up with a bunch of crazy nonsense on Facebook.", 'Showed her Tucker Carlson specials.', 'She watches Tucker Carlson and the Five, and sometimes just watches Fox all day.', 'She actually didn‚Äôt watch Fox News for some time after they booted Tucker Carlson but she is watching and listening to Fox News now.', 'She sent several Fox News videos of Tucker Carlson, Sean Hannity, and Laura Ingraham.'] | G59: Influence of Fox News and Tucker Carlson on QAnon Beliefs | I59: 2-Trigger-Influencers
A60: 60 | B60: 143 | C60: 185 | D60: 143_nightmare_sleep_dream_nightmares | E60: ['nightmare', 'sleep', 'dream', 'nightmares', 'sleeping', 'wake', 'dreams', 'schedule', 'bed', 'nights'] | F60: ['I just want to wake up from this nightmare.', 'Then my worst nightmare happened.', 'The whole Damar Hamlin story was a nightmare in my house.', 'EDIT: This is my worst nightmare.', 'This nightmare has been going on for nearly a year and I lose sleep nightly over it.'] | G60: Family Distress Over QAnon Involvement | J60: Narr's feeling
A61: 61 | B61: 144 | C61: 182 | D61: 144_cancer_diagnosed_stage_cure cancer | E61: ['cancer', 'diagnosed', 'stage', 'cure cancer', 'treatment', 'lung', '26', 'cure', 'survivor', 'passed away'] | F61: ['Mom is at risk with having had cancer.', "Even if cancer risk wasn't part of the equation, we need sunscreen.", 'So some years ago I was in the hospital with cancer.', 'You brought this cancer into our home.', "So my sister's friend has breast cancer."] | G61: Cancer and Health Concerns | I61: 0-Background-Health
A62: 62 | B62: 145 | C62: 182 | D62: 145_live life_take care_back normal_go back normal | E62: ['live life', 'take care', 'back normal', 'go back normal', 'normal life', 'normalcy', 'let live', 'want live', 'life want', 'normal people'] | F62: ['Take care of yourself, everyone.', 'Try to live your life instead and become the person you want to be.', 'I just want to live my life.', 'I hope all our loved ones can go back to more of a normal soon.', 'I just want everything to go back to normal.'] | G62: Desire for Normalcy and Personal Well-being | J62: Narr's feeling
A63: 63 | B63: 146 | C63: 181 | D63: 146_elected_season_2020 election_got elected | E63: ['elected', 'season', '2020 election', 'got elected', 'got worse', 'gotten worse', 'trump got elected', 'presidential election', '2016 election', '2016'] | F63: ['Fast forward to the 2016 election.', 'Even all of those years ago when Trump got elected, you could just feel like something bigger was coming down the line.', "It's gotten way worse since Trump got elected.", 'but when trump got elected it just got so much worse.', 'Sometime after Trump got elected, everything got worse.'] | G63: Impact of Trump's Election on QAnon Beliefs | I63: 2-Trigger-Election
A64: 64 | B64: 151 | C64: 172 | D64: 151_fight_fights_fighting_fought | E64: ['fight', 'fights', 'fighting', 'fought', 'got fight', 'want fight', 'tension', 'huge fight', 'big fight', 'fighting back'] | F64: ['Especially when that fight will do absolutely no good.', "I was so sick, I didn't have the fight in me to do anything but hear what was going on and wish it wasn't.", "I didn't talk back and I didn't fight.", 'Maybe 2 months after this fight the videos start back up.', 'as a means to not start a fight.'] | G64: Family Conflict Over QAnon Beliefs | H64: Narrator stops fighting | I64: 3-Oon after-Impact to narr
A65: 65 | B65: 153 | C65: 169 | D65: 153_bipolar_mental illness_illness_disorder | E65: ['bipolar', 'mental illness', 'illness', 'disorder', 'mentally ill', 'psych', 'mental health', 'mentally', 'psychiatrist', 'ill'] | F65: ["She doesn't believe in mental illness, because she isn't well.", 'A few things about her: \n- Her mother had bipolar issues and she almost certainly suffers from some sort of mental illness, depression has been an issue for her in the past.', 'I also believe that she has undiagnosed bipolar disorder or borderline personality disorder.', "Despite being diagnosed as bipolar, she says she's not now.", 'The doctors have tried different medication ‚Äúcocktails.‚Äù She is suffering from depression, anxiety and was diagnosed with bipolar disorder at a psych ward.'] | G65: Mental Health and QAnon Involvement | H65: Mental Health Issues from Qanon Believers | I65: 0-Background-Mental State
A66: 157 | B66: 419 | C66: 167 | D66: 156_empathy_compassion_compassionate_empathetic | E66: ['empathy', 'compassion', 'compassionate', 'empathetic', 'empathize', 'nice', 'kindness', 'understanding', 'lack', 'sympathy'] | F66: ['He does not show compassion love or empathy and that is my fault he says.', 'love and compassion and empathy for fucking everyone.', 'But, with what he says and does I just can‚Äôt have any compassion or empathy for him at this point.'] | G66: Loss of Compassion and Empathy in Loved Ones | I66: 3-Oon after-Behavior/action
A67: 66 | B67: 155 | C67: 168 | D67: 155_mental health_toll_taking toll_mental health issues | E67: ['mental health', 'toll', 'taking toll', 'mental health issues', 'mental illness', 'affecting', 'illness', 'professional', 'depression', 'health issues'] | F67: ["Because this isn't good for my mental health.", "Ruminating on it hasn't been good for my mental health.", 'That will help my mental health!', 'How does anyone deal with this while not compromising their mental health?', 'I had to for my own mental health.'] | G67: Impact of QAnon on Mental Health | H67: (Negative) Impact? | I67: 3-Oon after-Impact to narr
A68: 67 | B68: 157 | C68: 164 | D68: 157_anger_emotions_rage_sadness | E68: ['anger', 'emotions', 'rage', 'sadness', 'angry time', 'frustration', 'emotion', 'angry sad', 'consuming', 'describe'] | F68: ["But getting my emotions to fall in line with that, just isn't possible.", 'There‚Äôs just so many emotions about all this.', "If I'm angry at someone the anger never lasts long.", 'What do I do about this anger?', 'I stewed in the anger for about a day.'] | G68: Emotional Struggles with Anger | I68: 3-Oon after-Impact to narr | J68: Narr's feeling
A69: 68 | B69: 158 | C69: 160 | D69: 158_shocked_surprised_shock_disappointed | E69: ['shocked', 'surprised', 'shock', 'disappointed', 'surprise', 'shocking', 'surprising', 'stunned', 'say least', 'omg'] | F69: ['I‚Äôm just so shocked and disappointed.', 'I was disappointed, but not shocked.', 'I‚Äôm so shocked and disappointed and...worried.', 'I was shocked, and pleasantly surprised.', 'He was surprised, but not shocked.'] | G69: Emotional Reactions to QAnon Involvement | H69: (shock and disappointment) | I69: 3-Oon after-Impact to narr
A70: 69 | B70: 160 | C70: 156 | D70: 160_still love_want around_love much_want life | E70: ['still love', 'want around', 'love much', 'want life', 'get back', 'love lot', 'much miss', 'love even', 'love like', 'around like'] | F70: ['I barely want to be around them lately and it‚Äôs honestly sad.', 'I don‚Äôt want to be around them, like at all.', 'I don‚Äôt want to be around them and I don‚Äôt want them in my life.', 'We still love them though.', 'I still love them though.'] | G70: Strained Family Relationships Due to QAnon Involvement | H70: Narrator not wanting to be around Q people (but conflicted) | I70: 3-Oon after-Impact to narr
A71: 70 | B71: 161 | C71: 155 | D71: 161_evidence_misinformation_proof_claims | E71: ['evidence', 'misinformation', 'proof', 'claims', 'sources', 'proven', 'proven wrong', 'claim', 'facts', 'prove'] | F71: ['It was about the misinformation.', 'What is anecdotal evidence and what makes this type of evidence weak?', "But there's absolutely *no* evidence at all to support this claim.", 'Evidence doesn‚Äôt seem to do much.', "It, doesn't matter what my evidence was or where it came from."] | G71: Challenges of Debunking Misinformation | H71: Challenges of Resistance to | I71: 3-Oon after-Behavior/action
A72: 71 | B72: 163 | C72: 154 | D72: 163_optimistic_hopeful_hope best_think hope | E72: ['optimistic', 'hopeful', 'hope best', 'think hope', 'hopefully', 'hope right', 'much hope', 'chance', 'like best', 'still hope'] | F72: ['It might just be my hopeful thinking.', 'I am hopefully but not sadly not optimistic.', "I guess for now, I'm cautiously optimistic.", 'I need some hope but I am not optimistic.', 'We have to remain optimistic and hopeful.'] | G72: Cautious Optimism and Hope | J72: Narr's feeling
A73: 72 | B73: 164 | C73: 154 | D73: 164_gold_silver_currency_bank | E73: ['gold', 'silver', 'currency', 'bank', 'banks', 'buying', 'crypto', 'market', 'collapse', 'dollars'] | F73: ["She's been buying little tiny gold bars off the internet for a few years now with her savings and getting silver from a local coin dealer...", "She said she's 'excited' for the days to come, because the Vatican has been raided and all the gold has been captured and America will no longer be on a system of currency, but live on a system of gold.", 'She has also spent over 1k on buying silver after these qanon group chats said silver would be worth far more than gold.', 'She dragged me to the gold and silver store that featured ACTUAL SILVER COINS WITH HIS FUCKING HEAD ON THEM.', "Because of this, she's convinced gold and silver will take over as the primary currencies of the world."] | G73: Precious Metals Investment Beliefs in QAnon | I73: 3-Oon after-Behavior/action
A74: 73 | B74: 169 | C74: 152 | D74: 169_communist_communism_socialist_socialism | E74: ['communist', 'communism', 'socialist', 'socialism', 'communists', 'revolution', 'democratic', 'democrat', 'america', 'labeled'] | F74: ["That's what communism is now?", 'He just talked to me for 3 hours about communism and the above.', 'So they hate communism right?', 'Your belief and your hate for Trump or enough for you to watch your Country turn socialist and then communist as every country in the world that was ever socialist resulted in communism and watch your family go to concentration camps for their beliefs and not vaccination which are now bio weapons.', 'Socialism = Communism and Capitalism is the only way.'] | G74: Fear of Communism and Socialism | H74: Fear of Criticism towards | I74: 3-Oon after-Belief
A75: 74 | B75: 172 | C75: 142 | D75: 172_food_water_hoarding_stock | E75: ['food', 'water', 'hoarding', 'stock', 'canned', 'prepper', 'foods', 'prepping', 'stocking', 'supplies'] | F75: ['My conspiritual mother has been begging me to stock up on water, candles, blankets and canned food because this winter it is going to go down.', 'They are also hoarding canned foods and water which they consider "prepping".', 'Stock up on food and water.', 'Dehydrated food, flashlights and radios and chargers.', "I'm not the one who is storing food."] | G75: Prepping and Hoarding Supplies | I75: 3-Oon after-Behavior/action
A76: 75 | B76: 173 | C76: 140 | D76: 173_exhausted_tired_numb_emotionally | E76: ['exhausted', 'tired', 'numb', 'emotionally', 'drained', 'sick tired', 'mentally', 'fatigue', 'depressed', 'whole thing'] | F76: ['I‚Äôm exhausted from it all.', "I'm so exhausted from the mental gymnastics.", "I'm exhausted, what can I do?", 'So exhausted but almost there.', 'I am so exhausted and tired.'] | G76: Emotional Exhaustion from QAnon Involvement | I76: 3-Oon after-Impact to narr
A77: 76 | B77: 174 | C77: 140 | D77: 174_cat_cats_boxes_schools | E77: ['cat', 'cats', 'boxes', 'schools', 'identify', 'animals', 'station', 'come get', 'dogs', 'identifying'] | F77: ['We were talking about his cat.', 'I told him on the phone I had to get our cat put down today.', "Those lilies can't be out where the cat will get to them.", 'Not so much the cat though.', "They have a cat, so I told my mother that lilies are highly toxic to cats and she can't have the lilies where the cat will get to them."] | G77: Pet Safety Concerns Regarding Cats | H77: ??? | I77: ???
A78: 77 | B78: 175 | C78: 139 | D78: 175_pandemic_pandemic started_since pandemic_plandemic | E78: ['pandemic', 'pandemic started', 'since pandemic', 'plandemic', 'beginning pandemic', 'pandemic hit', 'ever since', 'beginning', 'went deep', 'start pandemic'] | F78: ['She always tells me this pandemic is all about the money.', 'She still calls the pandemic the "scamdemic."', 'And she calls the pandemic a "pland-emic".', 'It seemed that as the pandemic were on, she became more and more cemented in her views.', 'But the pandemic changed her.'] | G78: Pandemic Conspiracy Beliefs | I78: 3-Oon after-Belief
A79: 78 | B79: 176 | C79: 139 | D79: 176_live parents_still live_still living_financially | E79: ['live parents', 'still live', 'still living', 'financially', 'financial', 'parents since', '34', 'financially dependent', 'parents brother', 'dependent'] | F79: ['Still live with my parents because housing prices are insane.', 'My son and I live with my parents.', "I'm F21 and still live with my parents unfortunately.", 'I still live with my parents.', 'I still live with my parents due to money issues.'] | G79: Adult Children Living with Parents Due to Financial Constraints | I79: 0-Background-Living condition
A80: 79 | B80: 177 | C80: 138 | D80: 177_book_books_author_recommend | E80: ['book', 'books', 'author', 'recommend', 'guide', 'published', 'chapter', 'library', 'though family', 'shop'] | F80: ['I‚Äôd like to bring it forth as a book to recommend to everyone in this subreddit, as I found that the list of resources/books did not include this one book specifically.', "I've tried reading the book and listening to the audiobook, but it's just so long.", 'Oh, it‚Äôs in the book.', 'There was always a new book to read.', 'That could be a book in and of itself.'] | G80: Books and Recommendations in QAnon Context
A81: 80 | B81: 178 | C81: 137 | D81: 178_5g_towers_radiation_cell | E81: ['5g', 'towers', 'radiation', 'cell', 'bill gates', 'gates', 'phones', 'bill', 'brains', 'rubbish'] | F81: ['She talks about 5g being dangerous.', 'Then he goes on to tell us how 5G is melting her brain and other crap.', '5G is bad and they will control all of you.', 'Is that a 5g thing?', 'It all started with 5G.'] | G81: 5G Conspiracy Theories | I81: 3-Oon after-Belief
A82: 180 | B82: 179 | C82: 137 | D82: 179_addiction_addict_addicted_drug | E82: ['addiction', 'addict', 'addicted', 'drug', 'addictive', 'drugs', 'recovering', 'someone love', 'like watching', 'loved one'] | F82: ["I know about addiction, I'm a recovering addict but this is way way over my head.", 'This is no worse than a drug addiction.', "It's almost an addiction in and of itself."] | G82: Addiction-like Behavior in QAnon Belief | J82: Perception of Q
A83: 81 | B83: 181 | C83: 136 | D83: 181_14_18_minor_33 | E83: ['14', '18', 'minor', '33', '30s', '16', '40s', '20s', 'years old', 'thirties'] | F83: ['They said that I\'m "their minor," so I (and my body, I assume) am theirs until I\'m 18.', 'So now, despite the fact that I‚Äôm in my early 20s and can barely keep myself afloat, I‚Äôm now taking care of a 16 year old girl.', "I'm 14 now, obviously, almost 15.", 'i was about 16-18 for all of this.', "**Edit:** Yes, I'm still a minor, but I turn 18 in less than a month."] | G83: Family Dynamics and Responsibilities Involving Minors
A84: 82 | B84: 182 | C84: 136 | D84: 182_pandemic_since pandemic_beginning pandemic_pandemic started | E84: ['pandemic', 'since pandemic', 'beginning pandemic', 'pandemic started', 'beginning', 'pandemic hit', 'pre', 'pandemic began', 'move back', 'start pandemic'] | F84: ["It's been a struggle since the pandemic started to keep a relationship with them, but pre-pandemic we were able to keep politics out and my son to have a great relationship with his grandpa.", 'My mom died at the beginning of the pandemic.', 'Thinking about leaving this family when this pandemic is over.', "My mom wasn't the same ever since the pandemic.", 'Before the pandemic, my mother moved in with me.'] | G84: Family Strain During Pandemic | I84: 2-Trigger-Pandemic
A85: 83 | B85: 183 | C85: 135 | D85: 183_freedom_war_constitution_freedoms | E85: ['freedom', 'war', 'constitution', 'freedoms', 'amendment', 'policy', 'federal government', 'governments', 'allies', 'constitutional'] | F85: ['They shriek about the constitution and how it‚Äôs in peril, yet are constitutionally illiterate.', "You think we're in a war?", 'We have to face the hate head on - and if that means war, it means war.', "That's the beauty of freedom and independence.", 'But without that unease, there is no freedom.'] | G85: Constitutional Concerns and Freedom Narratives | H85: ??? | I85: ???
A86: 84 | B86: 184 | C86: 134 | D86: 184_boundaries_boundary_setting_setting boundaries | E86: ['boundaries', 'boundary', 'setting', 'setting boundaries', 'set boundary', 'set boundaries', 'respect boundaries', 'firm', 'respected', 'respect'] | F86: ['Because they do not understand boundaries.', "The boundaries aren't working so....", 'And if they have any issue on my boundaries that I will set, that we will have a problem.', "I guess boundaries don't really mean anything to these people.", 'Do my boundaries seem okay?'] | G86: Boundary Challenges in QAnon Relationships | I86: 3-Oon after-Behavior/action
A87: 85 | B87: 186 | C87: 134 | D87: 186_believes things_believe things_want believe_told believe | E87: ['believes things', 'believe things', 'want believe', 'told believe', 'believe stuff', 'even said', 'still believes', 'believe told', 'saying believe', 'know believes'] | F87: ['She believes these things without question.', "And it's from the same woman that somehow believes all these things simultaneously somehow.", 'She believes some of the things but not all of them.', 'I‚Äôm literally astonished she believes these things.', 'She believes in those things... Out of desperation.'] | G87: Unwavering Belief in Conspiracy Narratives | I87: 3-Oon after-Behavior/action
A88: 87 | B88: 189 | C88: 131 | D88: 189_lizard_lizard people_clones_clone | E88: ['lizard', 'lizard people', 'clones', 'clone', 'queen', 'earth', 'aliens', 'people real', 'clinton', 'executed'] | F88: ['They are clones or lizard people.', 'And there are lizard people!', 'lizard people who are -- there, for some reason?', 'That they are lizard people or working with the lizard people.', '(Where are the lizard people pics?)'] | G88: Belief in Lizard People Conspiracy | I88: 3-Oon after-Belief
A89: 88 | B89: 191 | C89: 131 | D89: 191_go contact_cut contact_low contact_cutting contact | E89: ['go contact', 'cut contact', 'low contact', 'cutting contact', 'went contact', 'low', 'contact since', 'limited contact', 'gone contact', 'going contact'] | F89: ['I cannot cut contact but the contact to them is not good for me.', 'Is there a way to have a relationship, or do I need to cut contact?', 'For these reasons we are low contact not no contact.', "I'm not at a place where I want to go no-contact.", 'Did you go no contact?'] | G89: Managing Contact with QAnon-Influenced Relatives | H89: …no/low Contact... | I89: 3-Oon after-Impact to narr
A90: 89 | B90: 192 | C90: 129 | D90: 192_decision_options_choice_right decision | E90: ['decision', 'options', 'choice', 'right decision', 'made right', 'make decision', 'dilemma', 'option', 'weighing', 'decisions'] | F90: ["I'm sorry if I made the wrong decision.", 'It was/is a hard decision to make.', "And I hope I didn't make the wrong decision.", 'This was probably a good decision.', 'It is the principled decision.'] | G90: Decision-Making Dilemmas | J90: Narr's feeling
A91: 90 | B91: 194 | C91: 127 | D91: 194_heart goes_breaks_breaks heart_broken | E91: ['heart goes', 'breaks', 'breaks heart', 'broken', 'heart breaks', 'heart breaking', 'breaking heart', 'broke heart', 'breaking', 'hearts'] | F91: ['The thought breaks my heart.', 'It breaks my heart that this is happening.', 'It really breaks my heart, man.', 'Now, that breaks my heart!', 'it breaks my heart that this was too much to ask for.'] | G91: Heartbreak Over Family Involvement in QAnon | I91: 3-Oon after-Impact to narr
A92: 91 | B92: 196 | C92: 126 | D92: 196_jfk_jr_jfk jr_alive | E92: ['jfk', 'jr', 'jfk jr', 'alive', 'still alive', 'kennedy', 'michael', 'assassination', 'john', 'dead'] | F92: ['The whole JFK JR being alive too... (And a republican!?', '"Have you heard of JFK Jr?"', 'Some nonsense about JFK Jr being Q himself.', 'What is their fascination with JFK Jr?', 'He believes that JFK Jr. is alive.'] | G92: Belief in JFK Jr. Being Alive | I92: 3-Oon after-Belief
A93: 92 | B93: 197 | C93: 125 | D93: 197_kamala_kamala harris_harris_wins | E93: ['kamala', 'kamala harris', 'harris', 'wins', 'vote', 'win', 'voted', 'voting', 'biden', 'president'] | F93: ['I want Kamala to win, but I‚Äôll never hear the end of it from my parents if she does.', 'I didn‚Äôt mention the republicans who have endorsed Kamala Harris.', 'Until tonight, when my father brought up Kamala Harris.', '**\xa0\xa0\xa0**He is the husband of KAMALA HARRIS!', 'She called Kamala Harris ‚Äústupid‚Äù.'] | G93: Family Reactions to Kamala Harris and 2020 Election | I93: 3-Oon after-Belief
A94: 93 | B94: 198 | C94: 125 | D94: 198_autistic_autism_diagnosed_spectrum | E94: ['autistic', 'autism', 'diagnosed', 'spectrum', 'functioning', 'undiagnosed', 'severe', 'syndrome', 'adhd', 'affects'] | F94: ['My partner, as I‚Äôve mentioned, is autistic.', 'As I just mentioned, my daughter is autistic.', 'Two of them are autistic (I am too by the way - it seems to be hereditary).', 'Even being autistic i can read that face.', 'he does not know i‚Äôm autistic.'] | G94: Autism and QAnon Involvement | J94: narr+others
A95: 94 | B95: 199 | C95: 125 | D95: 199_adrenochrome_blood_drink_drink blood | E95: ['adrenochrome', 'blood', 'drink', 'drink blood', 'harvesting', 'harvest', 'blood libel', 'libel', 'children blood', 'elite'] | F95: ['&#x200B;\n\nQuestion 2: Where is this Adrenochrome business coming from?', 'Then the adrenochrome stories started.', 'I asked them if they knew what adrenochrome was.', 'Even the whole adrenochrome crap.', 'The whole adrenochrome thing still real.'] | G95: Adrenochrome Conspiracy Beliefs | I95: 3-Oon after-Belief
A96: 95 | B96: 200 | C96: 123 | D96: 200_arrested_arrests_jail_trial | E96: ['arrested', 'arrests', 'jail', 'trial', 'crimes', 'criminal', 'charges', 'convicted', 'arrest', 'possession'] | F96: ["That there's going to be mass arrests.", 'I can‚Äôt wait until all these stupid people are arrested.', 'I think he got reckless as he got arrested but was let out awaiting trial.', 'He was arrested by the cops and taken to jail, but was released shortly after.', 'He believes some have been in jail for years with no trial.'] | G96: Legal Consequences of QAnon Involvement | I96: 3-Oon after-Legal
A97: 96 | B97: 202 | C97: 121 | D97: 202_divorce_filed_divorced_married | E97: ['divorce', 'filed', 'divorced', 'married', 'marriage', 'divorcing', 'option', 'papers', 'separated', 'signed'] | F97: ['I don‚Äôt know if this is divorce worthy.', 'They didn‚Äôt divorce, but didn‚Äôt see each other often.', 'In the end, it didn‚Äôt weigh in at all around the divorce.', 'Divorce was brought up by me in the conversation.', 'I am the one who asked for the divorce.'] | G97: Marital Strain Due to QAnon Involvement | I97: 3-Oon after-Social
A98: 97 | B98: 203 | C98: 121 | D98: 203_realities_alternate_alternate reality_two different | E98: ['realities', 'alternate', 'alternate reality', 'two different', 'separate', 'totally different', 'like two', 'bye', 'shifting', 'touch reality'] | F98: ['We truly live two different realities.', '), inside jobs everywhere, alternate realities, ... you guys know.', 'It‚Äôs like we live in two differet realities with no way to reach the other side.', "I'm just afraid that our realities are no longer congruent, and where can any couple go from there?", 'These things are two separate alternate realities.'] | G98: Divergent Realities in Relationships | I98: ??? | J98: Narr's feeling
A99: 98 | B99: 205 | C99: 120 | D99: 205_personality_lost mind_bitter_gotten much worse | E99: ['personality', 'lost mind', 'bitter', 'gotten much worse', 'gotten much', 'temper', 'much worse', 'erratic', 'gotten worse', 'big part'] | F99: ["It just doesn't fit his personality.", 'It was a part of his personality.', 'He has to make it his personality.', 'Little by little his personality changed.', 'Is this just his personality now?'] | G99: Personality Changes Due to QAnon Involvement | I99: 3-Oon after-Behavior/action
A100: 99 | B100: 209 | C100: 118 | D100: 209_pizzagate_pizza_gate_pizza gate | E100: ['pizzagate', 'pizza', 'gate', 'pizza gate', 'wayfair', 'gates', 'bill gates', 'mentions', 'bill', 'basement'] | F100: ['The whole pizza gate and all that.', 'Often they start with Pizzagate.', '(I thought Pizzagate definitely did.)', '"Did you hear about Pizzagate??"', 'He went into what was known as pizzagate.'] | G100: Pizzagate Conspiracy Narratives | I100: 3-Oon after-Belief
...

Sheet topics_merged
B1: (Color coded: Green = OK, Pink = So-so, can be better, Orange = Needs refinement, White = Not sure if we want to keep / what label to give
B2: Topic | C2: Count | D2: Name | E2: Representation | F2: Representative_Docs | G2: GPT Label | H2: Better Label? | I2: Category (0 - Background, 1 - Oon before, 2 - Trigger, 3 - Oon after) | J2: Remarks
A3: 0 | B3: 1 | C3: 3225 | D3: 1_mom back_want mom_mom mom_mum | E3: ['mom back', 'want mom', 'mom mom', 'mum', 'love mom', 'relationship mom', 'miss', 'mom always', 'mom want', 'like mom'] | F3: ['I just want my mom back.', 'I want my mom back.', 'I just want my mom back.', 'I just want my mom back.', 'Seriously I want my mom back.'] | G3: Desire for Reconnection with Mother | J3: Narr's needs
A4: 1 | B4: 3 | C4: 2615 | D4: 3_dad dad_love dad_dad always_like dad | E4: ['dad dad', 'love dad', 'dad always', 'like dad', 'miss', 'stepdad', 'know dad', 'dad would', 'dad never', 'step dad'] | F4: ['My dad was always easier.', 'My dad and I have always had a rocky relationship.', 'I love my dad but this is tough to say the least.', 'Despite everything, I love my dad and can‚Äôt help but mourn the childhood I spent with him.', 'I love my dad a lot.'] | G4: Strained Father-Child Relationships Due to QAnon | I4: 3-Oon after-Social
A5: 2 | B5: 4 | C5: 2572 | D5: 4_text_screamed_mad_hung | E5: ['text', 'screamed', 'mad', 'hung', 'argue', 'texted', 'answer', 'stop talking', 'want talk', 'upset'] | F5: ['He asks a lot of questions and I just try to answer them or look them up with him.', 'He started screaming at me, I told him not to raise his fucking voice at me while I‚Äôm trying to have a convo with him and hung up.', 'I was hyperventilating and crying uncontrollably and he interpreted it as me trying to scare him like I was mad or something so he just yelled louder until he left eventually.', 'He‚Äôll discuss it, but he gets pretty upset if you actually bring up good points.', "He knows I don't want to hear it, but he likes making me mad."] | G5: Family Conflict Over QAnon Beliefs | H5: Q's Hostile Behavior towards others | I5: 3-Oon after-Behavior/action
A6: 3 | B6: 5 | C6: 1981 | D6: 5_text_argue_spoken_want talk | E6: ['text', 'argue', 'spoken', 'want talk', 'hung', 'texting', 'answer', 'thanked', 'talk anymore', 'disagree'] | F6: ["I haven't spoken to her since then and it's been about a month.", 'She just want to agree to disagree, I want to discuss the matter, understand her reasoning... so in the end we just agree to disagree.', "Who's going to argue with her?", 'I have yet to text her back.', "I didn't see the text so she called."] | G6: Family Communication Breakdown Due to QAnon Beliefs | I6: 3-Oon after-Behavior/action
A7: 4 | B7: 13 | C7: 1121 | D7: 13_doctor_doctors_cancer_hospital | E7: ['doctor', 'doctors', 'cancer', 'hospital', 'medical', 'meds', 'medicine', 'medication', 'cure', 'treatment'] | F7: ['(Give her cancer or something).', 'Not to mention SHE IS A DOCTOR!!!', 'I urged her to get to her doctor.', 'You cannot just look at her and say she‚Äôs not a doctor.', "She is the hospital right now, and I don't how long she's had the cancer yet."] | G7: Family Impact of Medical Misinformation in QAnon Context | H7: Distrust in doctors? | I7: 3-Oon after-Behavior/action
A8: 5 | B8: 20 | C8: 850 | D8: 20_oxygen_hospital_doctor_doctors | E8: ['oxygen', 'hospital', 'doctor', 'doctors', 'medical', 'heart attack', 'diabetes', 'medication', 'cancer', 'failure'] | F8: ['He is over 70 and has diabetes, high blood pressure, and congestive heart failure.', 'His wife has been sick and is now in hospital.', 'And after evaluating him they decided to bring him to a mental hospital.', 'After getting out of the hospital.. he was not the same.', 'His blood oxygen when he made it to the ER was 76.'] | G8: Health and Medical Issues Related to QAnon Beliefs | H8: Related to QAnon Beliefs | I8: 0-Background-Health
A9: 6 | B9: 29 | C9: 630 | D9: 29_sisters_siblings_brothers_older | E9: ['sisters', 'siblings', 'brothers', 'older', 'little sister', 'older sister', 'told brother', 'younger', 'niece', 'younger sister'] | F9: ['Two of my older sisters feel the same way more or less.', "My older sister has begun to just ignore my mom, while my little sister (who has autism) is very upset that she can't make my mom understand she's being ridiculous.", 'i talked to my older sister about this too.', 'We were closer sisters than me and my blood sister.', 'She is mad at me and my 2 sisters.'] | G9: Family Dynamics and QAnon Influence on Sibling Relationships | H9: QAnon Influence on Family Dynamics (Sibling Relationships) | I9: 3-Oon after-Impact to others
A10: 7 | B10: 31 | C10: 618 | D10: 31_drops_believer_related_full blown | E10: ['drops', 'believer', 'related', 'full blown', 'blown', 'er', 'followers', 'anonymous', 'believers', 'discovered'] | F10: ['He is a stout Q believer.', "I look through his posts, he's full blown Q guy, Trump is the savior, the whole thing.", 'He pretty quickly became a full blown q convert and stopped going into work more and more often so he could spend more time watching youtube and talking to other fellow believers.', 'Sorry for the rant..... anyway......\n\nNot only was everyone I was watching talking about "Q Drops"...but they were also all becoming..............extremely fond of Trump.', 'he calls Q drops and the videos from top Q believers on youtube the "new Bible" and tells me to throw my copies of the "old" one away.'] | G10: QAnon Belief and Influence on Personal Lives | H10: Full-blown stage into Q?
A11: 8 | B11: 34 | C11: 569 | D11: 34_daughter_rest family_parent_side family | E11: ['daughter', 'rest family', 'parent', 'side family', 'family really', 'kid', 'grandparent', 'people family', 'son', 'sees'] | F11: ['But it kills me knowing that the rest of my family has to deal with him.', 'The rest of my family wouldn‚Äôt engage the subject at all with him.', "i don't know what to do or how to be his daughter anymore.", "I'm his daughter, his only child.", 'What do I say to demonstrate that he should put his daughter first, above all of this crap??'] | G11: Family Struggles with QAnon Beliefs | H11: QAnon Influence on Family Dynamics | I11: 3-Oon after-Impact to others
A12: 9 | B12: 35 | C12: 556 | D12: 35_boyfriend_hes_cheated_divorce | E12: ['boyfriend', 'hes', 'cheated', 'divorce', 'dare', 'agrees', 'dating', 'lets', 'ex', 'goes along'] | F12: ["It started with him threatening to dox and expose her, but then it moved to threatening to harm her, her boyfriend and even her boyfriend's cat if she didn't come back to him.", 'I don‚Äôt think he agrees with her beliefs but he just kind of lets it happen.', "Then she met her boyfriend, let's call him Dave.", '(The TL;DR of that is she had a boyfriend but cheated on that guy with my friend, but I again veer into other topics).', 'Her base for divorce was \'Hes not awake, hes part of the cabal, hes keeping secrets from me, hes gay"....'] | G12: Relationship Strain Due to QAnon Beliefs | H12: ??? | I12: 0-Background-Partner
A13: 10 | B13: 39 | C13: 523 | D13: 39_insanity_crazy one_madness_sane | E13: ['insanity', 'crazy one', 'madness', 'sane', 'sanity', 'craziness', 'like crazy', 'think crazy', 'going crazy', 'going insane'] | F13: ['I feel like I‚Äôm the crazy one.', "I don't think I have it in me to deal with any more of this insanity.", 'The man lost *everything* to this insanity.', "I'm so sick of the insanity.", 'When does this insanity end?'] | G13: Family Struggles with QAnon-Induced Insanity | H13: Family Struggles
A14: 11 | B14: 40 | C14: 523 | D14: 40_missing_saving children_protect_saving | E14: ['missing', 'saving children', 'protect', 'saving', 'safety', 'kid', 'save children', 'abuse', 'kids want', 'child abuse'] | F14: ['The estrangements were painful for these parents and in an attempt to help them process what was happening, the essay author noticed a trend of ‚Äúmissing missing reasons.‚Äù TL;DR these estranged parents almost uniformly were unable to say why they had been cut off by their adult children.', 'I am so frustrated with this "missing children" crap.', 'In many countries, statistics on missing children are not even available; and, unfortunately, even available statistics may be inaccurate due to: under-reporting/under-recognition; inflation; incorrect database entry of case information; and deletion of records once a case is closed.‚Äù \n\nand also\n\n ‚Äú250,000 children are reported missing every year in the EU, 1 child every 2 minutes‚Äù\n\ni know that the vast majority of these reported cases are custody disputes between estranged parents, but he is completely sold that these kids are legitimately abducted and trafficked, despite that being an absolutely insane number, and wouldn‚Äôt that constitute the biggest news story of our times!?', 'You thought you were saving children?', 'And where the hell are all the missing migrant children?!?!?!?!?!'] | G14: Concerns about Missing and Abducted Children | H14: Q's Belief "Save the Children" | I14: 3-Oon after-Belief
A15: 12 | B15: 42 | C15: 496 | D15: 42_relationships_strained_end relationship_repair | E15: ['relationships', 'strained', 'end relationship', 'repair', 'good relationship', 'strain relationship', 'strain', 'surface level', 'time together', 'complicated'] | F15: ['Things have been strained between the two of us since.', "In other words, it's time for me to triage my relationships.", 'I had been in several dysfunctional relationships but this was the worst.', 'Sometimes those relationships can be mended; sometimes they can‚Äôt be.', 'Suffice it to say the relationships are very strained.'] | G15: Strained Relationships Due to QAnon Involvement | I15: 3-Oon after-Social
A16: 13 | B16: 43 | C16: 493 | D16: 43_black_racist_white_racism | E16: ['black', 'racist', 'white', 'racism', 'black people', 'white people', 'race', 'brown', 'supremacy', 'color'] | F16: ['One of the things growing up that we both really struggled with was race and how having a white mother and black father was being too white for the black kids and too black for the white kids.', 'My boyfriend is black, his friend is white, and I am also white.', 'I am a black woman and my husband is a white man from the Midwest.', 'Im in a multiracial family, and often grapple with the fact that my father can be so racist when he has a black son and wife.', 'As far as racism goes everyone in the world is racist in some way.'] | G16: Interracial Relationships and Racism Experiences | I16: 0-Background-Race
A17: 14 | B17: 44 | C17: 484 | D17: 44_conversations_spoken_spoken since_communication | E17: ['conversations', 'spoken', 'spoken since', 'communication', 'end conversation', 'want talk', 'talk phone', 'talk anything', 'conversation went', 'small talk'] | F17: ['We‚Äôve had many of these conversations.', 'We were able to have real conversations.', 'Any conversations we have can be kept confidential for now.', 'We do not talk often so it never comes up in our conversations.', 'Our conversations were only about this.'] | G17: Communication Challenges in Conversations | H17: ??? | I17: ???
A18: 15 | B18: 45 | C18: 474 | D18: 45_ivermectin_horse_cure_paste | E18: ['ivermectin', 'horse', 'cure', 'paste', 'doctor', 'treat', 'doctors', 'medicine', 'doses', 'ordered'] | F18: ['and they with their buckets of ivermectin dgaf then, so why does it matter now?).', 'I have a question about ivermectin.', 'I said, "No, I won\'t be taking ivermectin.', "Ivermectin and hydroxychloroquine aren't working.", 'What effectiveness had ivermectin had anyway?'] | G18: Ivermectin Use and Skepticism in Treating Illness | I18: 3-Oon after-Belief
A19: 16 | B19: 50 | C19: 445 | D19: 50_currency_gold_silver_crypto | E19: ['currency', 'gold', 'silver', 'crypto', 'scam', 'debt', 'bank', 'dollar', 'banks', 'worthless'] | F19: ["He's been slowly funneling out our money to crypto currency that I don't have access to.", 'Thankfully he just bought gold and silver with it though.', 'My mom is spending hers and my dads life savings on crypto currency and also buying all sorts of worthless currency from EBay (Zimbabwe, Iraqi, Venezuelan currency).', 'Then somehow it turns into how we aren‚Äôt aware of what‚Äôs happening in this country and how currency is about to change to gold and silver and demanded that tomorrow he is going to buy gold!', 'He wants to put all our money into gold/silver purchases.'] | G19: Financial Decisions Influenced by Conspiracy Beliefs | I19: 3-Oon after-Behavior/action
A20: 17 | B20: 51 | C20: 443 | D20: 51_christmas_thanksgiving_holidays_holiday | E20: ['christmas', 'thanksgiving', 'holidays', 'holiday', 'celebrate', 'easter', 'eve', 'xmas', 'season', 'home christmas'] | F20: ['Christmas is just going to be different through and through.', 'I‚Äôm honestly thinking about skipping Christmas.', 'Most of my family spent Christmas day together.', 'Our Christmas traditions won‚Äôt be the same.', 'We usually spend Thanksgiving and Christmas with my family but not this year.'] | G20: Family Holiday Gatherings Affected by QAnon | I20: 3-Oon after-Impact to others
A21: 18 | B21: 52 | C21: 440 | D21: 52_step dad_told dad_step_even dad | E21: ['step dad', 'told dad', 'step', 'even dad', 'divorce', 'dad said', 'dad would', 'dad told', 'dad thinks', 'divorced'] | F21: ['She has threatened to divorce my dad after nearly 20 years of marriage because he expressed concern in her habits and behavior.', '(It at least makes me feel better that even my dad needed to see her freak out like this to realize how deep the manipulation went, and he was married to her for over 20 years before they divorced when I was in high school.', "she also said she couldnt text about it, could only talk on the phone wtf\n\ni texted my step dad saying i didn't appreciate her threatening me and to knock it off!", 'I told my dad (her son) that she hasn‚Äôt had an original thought for a long time because my step-grandpa won‚Äôt let her.', 'I am afraid she will lose my step dad.'] | G21: Family Strain Due to QAnon Beliefs | H21: (Stepdad) / manipulation | I21: 3-Oon after-Behavior/action
A22: 19 | B22: 53 | C22: 437 | D22: 53_weed_drugs_mental health_bipolar | E22: ['weed', 'drugs', 'mental health', 'bipolar', 'depression', 'addict', 'drug', 'drinking', 'schizophrenia', 'alcohol'] | F22: ["This is the same man that grew weed in our house growing up because then Government can't tell him what to do.", 'Keep in mind this person was outgoing and rebellious as a kid but growing up and after making poor decisions, from smoking weed to then more hard drugs such as meth, they‚Äôve became very different.', 'He has very strong anxiety and smokes a lot of weed.', 'Dmt, shrooms, weed, etc, should be stopped.', 'Also, he was not just on weed.'] | G22: Substance Use and Mental Health Issues | I22: 0-Background-Substance Use
A23: 20 | B23: 54 | C23: 427 | D23: 54_want kids_whole family_rest family_grandchild | E23: ['want kids', 'whole family', 'rest family', 'grandchild', 'son', 'extended family', 'see kids', 'family members', 'much family', 'contact family'] | F23: ["I swear she quotes all of the speaker's she sees I agreed with her and said I didn't want my kids to grow up with that outlook.", 'When she asked what kind of things I said things like who you want your kids to go to and medical things like a DNR.', 'She is in deep and says her whole family is as well.', "I've tried so hard to have a relationship with her for the sake of my kid, her own grandchild, because I know how much she loves him.", "She's estranged to the whole family, and I'm basically the only link I have from her to the rest of the family."] | G23: Family Estrangement Due to QAnon Beliefs | I23: 3-Oon after-Impact to others
A24: 21 | B24: 55 | C24: 412 | D24: 55_therapy_therapist_counseling_therapists | E24: ['therapy', 'therapist', 'counseling', 'therapists', 'couples', 'counselor', 'appointment', 'session', 'sessions', 'insurance'] | F24: ['And I‚Äôm still in therapy.', 'I have done the most therapy(by far).', 'I‚Äôm working on it with therapy.', "I've been through years of therapy.", 'I have recently been going to therapy to deal with these issues.'] | G24: Coping with QAnon-Related Family Strain through Therapy | I24: 3-Oon after-Impact to narr
A25: 22 | B25: 56 | C25: 405 | D25: 56_arguments_arguing_argue_argument | E25: ['arguments', 'arguing', 'argue', 'argument', 'debate', 'disagree', 'agree disagree', 'civil', 'debating', 'argued'] | F25: ["These weren't the only arguments we had about this, there was more.", "We've had these arguments already.", "We've never gotten into more arguments.", 'YOU TAKE ALL MY ARGUMENTS!', "Since then we've been fine, no arguments or anything at all."] | G25: Family Disputes Over QAnon Beliefs | H25: Family Arguments Over QAnon Beliefs | I25: 3-Oon after-Behavior/action
A26: 23 | B26: 58 | C26: 396 | D26: 58_mum_help mom_told mom_mom says | E26: ['mum', 'help mom', 'told mom', 'mom says', 'mom goes', 'get mom', 'agrees', 'mom mom', 'mom like', 'mom always'] | F26: ['Sometimes I just think about if his need for a car/help for his mom wasn‚Äôt in the picture, would he have stretched that timeframe of not wanting to be around me further?', 'I told my mom and she said he refuses to apologize since he was "tired when he said it".', 'We got passed him not wanting to see me because I am ‚Äúshedding‚Äù but a part of me believes that he only let me back in (being physically around him) because he needed help with his elderly mother (and not having car to help with his mom).', 'I am trying to help him and my mom to get into counseling for resolving there past conflict and become more open to one another.', 'He needed help with mom.'] | G26: Family Dynamics and Support Involving Mom | H26: ??? | I26: ???
A27: 24 | B27: 59 | C27: 394 | D27: 59_miss_love much_still love_feel bad | E27: ['miss', 'love much', 'still love', 'feel bad', 'senses', 'loves', 'want relationship', 'person used', 'come back', 'get back'] | F27: ['I want him to miss me too.', 'I miss him more than anything.', 'I just miss him so very, very much!', 'I miss him so much.', 'I just miss him and wish it wasn‚Äôt like this.'] | G27: Missing Loved Ones Due to QAnon Involvement | I27: 3-Oon after-Impact to narr
A28: 25 | B28: 60 | C28: 394 | D28: 60_cried_cry_crying_tears | E28: ['cried', 'cry', 'crying', 'tears', 'scream', 'sobbing', 'laugh', 'void', 'eyes', 'broke'] | F28: ['I cried because of how happy I was.', 'I cried so much already.', 'Maybe I cried all I could that day in the barn.', 'I cried, I was angry, I had so much sorrow, and I grieved.', 'I have cried so many tears and am on anti depressants to help me out.'] | G28: Emotional Distress and Coping | I28: 3-Oon after-Impact to narr
A29: 26 | B29: 64 | C29: 363 | D29: 64_older brother_brothers_older_younger brother | E29: ['older brother', 'brothers', 'older', 'younger brother', 'brother said', 'like brother', 'little brother', 'younger', 'brother told', 'lose'] | F29: ['My older brother has always walked on water in my eyes.', "I MISS MY OLDER BROTHER WHO I WISHED TO BE AS COOL AS GROWING UP BUT NOW I DON'T EVEN RECOGNIZE YOU.", 'My brothers are the same.', 'Both of my brothers have done this, it‚Äôs my turn.', 'My older brother was so special to us (lost him \\~7 years ago).'] | G29: Family Strain Due to QAnon Beliefs | H29: (Narrator-oon) Relationship with Brother? | I29: 0-Background-Relationship with narr
A30: 27 | B30: 66 | C30: 353 | D30: 66_twitter_facebook_fb_banned | E30: ['twitter', 'facebook', 'fb', 'banned', 'social media', 'account', 'https twitter', 'https twitter com', 'twitter com', 'instagram'] | F30: ['The best way to keep up on happenings is with these Twitter accounts:\n\n&#x200B;\n\n[https://twitter.com/fr\\_brennan](https://twitter.com/fr_brennan)\n\n[https://twitter.com/Kirtaner](https://twitter.com/Kirtaner)\n\n[https://twitter.com/AJVicens](https://twitter.com/AJVicens)\n\n[https://twitter.com/alibreland](https://twitter.com/alibreland)\n\n[https://twitter.com/AmericanHacker](https://twitter.com/AmericanHacker)\n\n[https://twitter.com/FoucaultMotoko](https://twitter.com/FoucaultMotoko)', 'He‚Äôs more active on twitter than fb.', "I looked down at my phone for something and saw the announcement that Trump's twitter account had been banned.", 'His Twitter account got banned a day before trump‚Äôs did.', 'I ask him to give up twitter (for a few days) and he can‚Äôt do that.'] | G30: Social Media and QAnon Involvement | I30: 2-Trigger-Social Media
A31: 28 | B31: 69 | C31: 345 | D31: 69_boundaries_bring back_like lost_want back | E31: ['boundaries', 'bring back', 'like lost', 'want back', 'breaks heart', 'feel like lost', 'want lose', 'breaks', 'get back', 'love much'] | F31: ['I feel like I lost her.', 'I feel like I lost her.', "I feel like she's lost to me.", 'he backed me up in my boundaries because he also has those boundaries with her, And is definitely the only reason why she is adhering to those boundaries right now.', 'She won‚Äôt adhere to my boundaries.'] | G31: Family Strain Due to QAnon Beliefs | I31: 3-Oon after-Impact to narr | J31: Narr's feeling
A32: 30 | B32: 73 | C32: 329 | D32: 73_youtube_algorithm_podcast_youtube videos | E32: ['youtube', 'algorithm', 'podcast', 'youtube videos', 'channel', 'algorithms', 'youtube com', 'youtube video', 'https', 'videos articles'] | F32: [' \n\nHello everyone,\n\nmy Name is Adrian and I am a journalist, working for the german television broadcast SPIEGEL TV MAGAZIN (Our YT-Channel: [https://www.youtube.com/user/spiegeltv](https://www.youtube.com/user/spiegeltv)).', 'Another interesting video I found on youtube is this one: [https://www.youtube.com/watch?v=NPHwO\\_sVSAQ](https://www.youtube.com/watch?v=NPHwO_sVSAQ).', 'I didn‚Äôt click on the YouTube video he sent because I didn‚Äôt want the algorithm to think I was interested in that.', 'But a lot comes from YouTube.', 'His youtube algorithm is nothing but this stuff.'] | G32: Impact of YouTube Algorithms on QAnon Content Consumption | I32: 2-Trigger-Social Media
A33: 31 | B33: 74 | C33: 327 | D33: 74_grief_grieving_mourning_grieve | E33: ['grief', 'grieving', 'mourning', 'grieve', 'betrayed', 'loss', 'like mourning', 'still alive', 'mourn', 'alive'] | F33: ['I felt the grief again.', "It feels like I'm grieving for someone who is still alive.", 'It feels like grieving a loss.', 'We are literally grieving the loss of our loved ones while they are still alive.', "I've honestly felt grief at the loss."] | G33: Grieving the Living | I33: 3-Oon after-Impact to narr
A34: 32 | B34: 78 | C34: 311 | D34: 78_pandemic_pandemic started_pandemic hit_since pandemic | E34: ['pandemic', 'pandemic started', 'pandemic hit', 'since pandemic', 'start pandemic', 'hit', 'pandemic really', 'pandemic began', 'beginning pandemic', 'got worse'] | F34: ["I'm frigging sick of this pandemic.", 'I hate what this pandemic has done to my kids‚Äô lives.', 'And then the pandemic happened.', "With the pandemic, it's been worse.", 'All well before the pandemic.'] | G34: Impact of the Pandemic on Personal Lives | I34: 2-Trigger-Pandemic
A35: 33 | B35: 81 | C35: 307 | D35: 81_baby_pregnant_pregnancy_first child | E35: ['baby', 'pregnant', 'pregnancy', 'first child', 'newborn', 'birth', 'born', 'expecting', 'grandchild', 'daughter'] | F35: ['How does anyone do this to their baby?!', 'We are having a baby soon.', "I kissed my baby's forehead and left.", 'I was just worried about my baby.', "Or, let's make love and make a baby."] | G35: Family and Pregnancy Concerns in QAnon Context | I35: 0-Background-Family
A36: 34 | B36: 83 | C36: 303 | D36: 83_retirement_lost job_fired_business | E36: ['retirement', 'lost job', 'fired', 'business', 'company', 'works', 'get job', 'retired', 'jobs', 'unemployed'] | F36: ['He hasnt lost his job yet, but it may happen.', 'Once he got to the U.S he worked a few odd jobs and started his own business.', 'They are maxed again and he is running out of retirement.', "He's a man nearing retirement age with a family.", 'He, the fucker, who‚Äôs close to retirement age anyway.'] | G36: Impact of QAnon on Employment and Retirement | H36: Impact of QAnon on | I36: 0-Background-Job
A37: 35 | B37: 86 | C37: 295 | D37: 86_sources_article_articles_source | E37: ['sources', 'article', 'articles', 'source', 'credible', 'reliable', 'proof', 'send', 'fake news', 'google'] | F37: ["I've sent her so many sources counteracting her and my uncle's claims.", 'I easily found multiple articles for each of her sources that debunked the information claimed and showed why these sources were not credible.', 'I asked her what sources she would trust.', 'I ask for sources and there is never any real source to back up the claims, but I "have to understand, she is getting this information from credible sources."', 'She won\'t listen to any fact, only these "sources".'] | G37: Credibility of Information Sources | H37: Q's unsourced belief? | I37: 3-Oon after-Behavior/action
A38: 36 | B38: 91 | C38: 279 | D38: 91_gates_bill gates_bill_5g | E38: ['gates', 'bill gates', 'bill', '5g', 'microchips', 'microchip', 'dna', 'vaccines', 'kill', 'population'] | F38: ['* Bill Gates - eugenics, decreasing the population, and vaccines\n* Globalism/NWO - George Soros, the Rockefellers, Jeff Bezos, Bill Gates, Klaus Schwabb, etc.', "And it was Bill Gates' company.", 'And of course the 5G, Covid, and Bill Gates conspiracies make sense to them.', 'Bill Gates is trying to implant microchips.', "I honestly still don't understand the Bill Gates thing."] | G38: Bill Gates and Conspiracy Theories | I38: 3-Oon after-Belief
A39: 37 | B39: 92 | C39: 276 | D39: 92_red_texas_florida_area | E39: ['red', 'texas', 'florida', 'area', 'rural', 'town', 'county', 'city', 'states', 'blue'] | F39: ['We live in a red state.', "We're also in a red state.", 'Still, he is deep in a red state.', 'We are from a very small rural red town.', 'I live in a very red area.'] | G39: Impact of QAnon in Conservative Rural Areas | H39: Demographics (red state) | I39: 0-Background-Political region
A40: 38 | B40: 99 | C40: 258 | D40: 99_racist_white_black_black people | E40: ['racist', 'white', 'black', 'black people', 'racism', 'race', 'racial', 'white supremacists', 'supremacists', 'white people'] | F40: ['He told me not to be racist.', 'That Trump is not now, nor has he ever been racist.', 'He is racist and he knows it.', 'It made him more racist.', 'He‚Äôs been doing this and making racist stereotypes.'] | G40: Racism and Racial Attitudes in QAnon Narratives | I40: 3-Oon after-Behavior/action
A41: 39 | B41: 100 | C41: 254 | D41: 100_anxiety_ocd_panic_panic attacks | E41: ['anxiety', 'ocd', 'panic', 'panic attacks', 'panic attack', 'attacks', 'attack', 'disorder', 'roof', 'depression'] | F41: ['Saying it was an anxiety attack.', 'Anxiety and panic attacks can mimic serious health issues which is compounding my fear.', 'I have an anxiety disorder and ocd.', 'I kept having panic attacks and my anxiety was so bad.', "Which I still haven't gotten myself to do because of the anxiety around it."] | G41: Anxiety and Panic Disorders | I41: 3-Oon after-Impact to narr
A42: 40 | B42: 102 | C42: 251 | D42: 102_stolen_election stolen_fraud_election fraud | E42: ['stolen', 'election stolen', 'fraud', 'election fraud', 'rigged', 'voter fraud', 'voter', 'election rigged', 'stolen election', 'believes election'] | F42: ['He said the election was stolen.', 'Thinks the election was stolen.', 'He thinks their election was stolen and is always angry.', 'They now believe the election was stolen.', 'They dont believe the election was stolen.'] | G42: Belief in Election Fraud | I42: 3-Oon after-Belief
A43: 42 | B43: 106 | C43: 247 | D43: 106_safety_dangerous_protect_risk | E43: ['safety', 'dangerous', 'protect', 'risk', 'careful', 'danger', 'bubble', 'precautions', 'feel safe', 'high risk'] | F43: ['and why it is so dangerous?', 'They‚Äôre crazy but they‚Äôre not dangerous.', 'This had me thinking about how dangerous this really is.', 'That said, risk was low but I have to be careful because we have at-risk people in our bubble.', 'I am not worried for my safety AT ALL.'] | G43: Concerns About Safety and Risk | I43: 3-Oon after-Impact to others
A44: 43 | B44: 107 | C44: 245 | D44: 107_moving_housing_rent_afford | E44: ['moving', 'housing', 'rent', 'afford', 'apartment', 'financially', 'next year', 'option', 'income', 'financially dependent'] | F44: ["As for moving out, I'm trying.", 'I am honestly thinking of moving out.', 'I am contemplating moving out.', "I can't even afford subsidized housing at this point in time because rent is just crazy (as it is getting to be everywhere it seems).", 'I can‚Äôt really afford to add more housing expenses.'] | G44: Financial Struggles with Housing and Moving Out | I44: 3-Oon after-Impact to narr
A45: 44 | B45: 109 | C45: 242 | D45: 109_leaving_walk away_walk_want leave | E45: ['leaving', 'walk away', 'walk', 'want leave', 'like leave', 'ride', 'need get', 'get feel', 'might make', 'exit'] | F45: ['How do you know when the only thing you can/should do is walk away?', 'When do I just walk away?', 'I decided we were leaving right then.', 'Do I need to give a reason why I‚Äôm leaving you behind?', "I'm ok with leaving if it doesn't work."] | G45: Leaving QAnon Involvement | H45: Narrator leaving Q people | I45: 3-Oon after-Social
A46: 45 | B46: 110 | C46: 239 | D46: 110_storm_fires_weather_fire | E46: ['storm', 'fires', 'weather', 'fire', 'snow', 'smoke', 'warm', 'burning', 'fuel', 'burn'] | F46: ['So...what exactly is The Storm, then?', 'But what happens after "the storm"?', 'And the fires in Hawaii?', 'Ok, I didn‚Äôt actually storm.', 'Do I just weather the storm?'] | G46: QAnon Conspiracy and Natural Disasters | I46: 3-Oon after-Belief
A47: 46 | B47: 111 | C47: 238 | D47: 111_doctors_beds_medical_med beds | E47: ['doctors', 'beds', 'medical', 'med beds', 'med', 'medicine', 'doctor', 'pharma', 'big pharma', 'medbeds'] | F47: ['I have seen doctors misdiagnose.', 'As they have made me petrified of doctors.', 'They put us off saying they needed to talk to their doctors.', "But the doctors haven't found a cause?", 'Most are *doctorates*, not medical doctors.'] | G47: Distrust in Medical Professionals | I47: 3-Oon after-Belief
A48: 47 | B48: 114 | C48: 226 | D48: 114_siblings_cousin_cousins_sibling | E48: ['siblings', 'cousin', 'cousins', 'sibling', 'aunts', 'uncle', 'older', 'aunt', 'aunt uncle', 'brothers'] | F48: ['I have many other siblings.', 'And I‚Äôm their only child, no siblings.', "Me and my siblings don't know what to do.", 'I just sorry for my siblings', 'My cousins were like siblings.'] | G48: Family Relationships and QAnon Impact | H48: [Oon-Narrator) Relationship - Siblings | I48: 0-Background-Relationship with narr
A49: 48 | B49: 115 | C49: 220 | D49: 115_trump supporter_supporter_politics_2016 | E49: ['trump supporter', 'supporter', 'politics', '2016', 'trump supporters', 'dad said', 'supporters', 'trumper', 'since 2016', 'voted'] | F49: ['I live in australia and my dad is a Trump supporter and has been since 2016 since then he had been watching Alex Jones, Fox News and some youtube‚Äôs supporting Trump.', 'My (F32) dad has always been a Trump supporter.', 'My dad is a Trump supporter.', '\n\nMy dad is very much a trump supporter.', 'My dad has been a Trump supporter for a while now.'] | G49: Parental Trump Support Since 2016 | I49: 0-Background-Political leaning
A50: 49 | B50: 117 | C50: 217 | D50: 117_2021_march_date_2016 | E50: ['2021', 'march', 'date', '2016', 'jan', 'january', '6th', 'october', 'february', 'august'] | F50: ['That was in August 2021.', "2021 hasn't been kind to me at all.", 'I cannot find a consecutive 3 days without any quarrel in 2021.', 'Back in the begging of 2021, we were talking about the election, Jan. 6th, etc.', 'but jan 6th on 2021 is what changed me completely for some reason.'] | G50: Impact of 2021 Events on Personal Lives
A51: 50 | B51: 119 | C51: 213 | D51: 119_satanic_satan_satanist_satanists | E51: ['satanic', 'satan', 'satanist', 'satanists', 'worshipping', 'hollywood', 'devil', 'pedophiles', 'panic', 'satanism'] | F51: ['He even posted the other day that everyone who is and voted for Democrats is a Satanic Pedophile.', 'My brother was once just a light Q in 2020 talking about Hollywood Satanic rituals.', '!‚Äù And ‚ÄúWhy the hell do you want to do this satanic major‚Äù.', 'Demons in inanimate objects, satanic music, satanic words, satanic rituals.', 'Believes in satanic paedophile rituals etc.'] | G51: Satanic Panic and QAnon Beliefs | H51: Satanic Perception and QAnon Beliefs | I51: 3-Oon after-Belief
A52: 51 | B52: 121 | C52: 210 | D52: 121_brainwashed_brainwashing_brain washed_washed | E52: ['brainwashed', 'brainwashing', 'brain washed', 'washed', 'brainwash', 'liberal', 'brain', 'leftist', 'believe everything', 'mind control'] | F52: ['You believe I‚Äôm brainwashed and I think The same.', 'It‚Äôs an entire country brainwashed.', 'How brainwashed and lost they are.', 'what if everyone really is brainwashed?', 'My brother is so fucking brainwashed.'] | G52: Family Struggles with Perceived Brainwashing | J52: Narr's feeling
A53: 52 | B53: 122 | C53: 210 | D53: 122_sheep_sheeple_black_brainwashed | E53: ['sheep', 'sheeple', 'black', 'brainwashed', 'wake', 'calling', 'calls', 'called stupid', 'eyes', 'blindly'] | F53: ['So my dad critizes me for my being a sheep.', "Will they tell him that he's stupid, he doesn't understand, he's wrong, he's a sheep, he's an embarrassment?", 'That I was a sheep.', 'He is now left to the sheep.', 'I, once again, am a beta man and sheep.'] | G53: Family Tensions Over "Sheep" Label in QAnon Beliefs | I53: ??? | J53: Oon's perception
A54: 53 | B54: 124 | C54: 208 | D54: 124_nurse_nurses_surgery_nursing | E54: ['nurse', 'nurses', 'surgery', 'nursing', 'doctor', 'doctors', 'er', 'hospital', 'grandma', 'asthma'] | F54: ['My mother is a Nurse Practitioner at a nursing home.', 'Her mother, an actual Nurse.', "I don't want to be a nurse anymore.", '‚ÄúBut mom, you‚Äôre a nurse.', 'The next was a friend I have who is a nurse.'] | G54: Healthcare Professionals and Family Dynamics | I54: ???
A55: 54 | B55: 127 | C55: 205 | D55: 127_guilt_guilty_feel guilty_embarrassed | E55: ['guilt', 'guilty', 'feel guilty', 'embarrassed', 'ashamed', 'embarrassing', 'shame', 'still feel', 'admit', 'guilt trip'] | F55: ['I feel guilty for some reason.', 'I feel plagued by guilt.', 'I don‚Äôt have that guilt anymore.', 'I have so much guilt.', 'You can deal with the self guilt later.'] | G55: Feelings of Guilt and Shame | I55: 3-Oon after-Impact to narr
A56: 55 | B56: 129 | C56: 204 | D56: 129_maga_ultra_movement_die hard | E56: ['maga', 'ultra', 'movement', 'die hard', 'branch', 'im tired', 'cult', 'hate filled', 'surrounded', 'sa'] | F56: ['My husband is MAGA and Q..basically the same thing to me.', 'In the name of MAGA.', 'I can‚Äôt deal with his transformation to a MAGA.', 'Now he is full MAGA.', 'So what about Trump and maga is so different than that?'] | G56: Family Struggles with MAGA/QAnon Beliefs | H56: Family Struggles with | I56: 3-Oon after-Belief
A57: 56 | B57: 132 | C57: 195 | D57: 132_forgive_apology_forgiveness_apologizing | E57: ['forgive', 'apology', 'forgiveness', 'apologizing', 'apologized', 'apologize', 'apologise', 'forget', 'owe', 'know ever'] | F57: ['With all that being said, I forgive you.', '& that‚Äôs okay, I forgive you.', 'I will never forgive him for this.', 'He‚Äôs very remorseful for everything and it‚Äôs taking a while for him to fully forgive himself.', 'He took money from my husband and I cannot forgive that.'] | G57: Family Forgiveness and Resentment | I57: 3-Oon after-Impact to narr | J57: But there're two different sentiments of narr?
A58: 57 | B58: 133 | C58: 192 | D58: 133_journalists_fake news_mainstream_mainstream media | E58: ['journalists', 'fake news', 'mainstream', 'mainstream media', 'news sources', 'bias', 'fake', 'sources', 'outlets', 'journalism'] | F58: ['It\'s all "fake news".... ... ... ... ... ... ... ... really?', 'I understand mainstream media is not perfect and of course they have their own bias they make mistakes they even lie sometimes but atleast I know there mostly credible, studied journalists and don‚Äôt want to ruin reputation.', '"How can you know when you only read "fake news" and the mainstream media and what "they" want you to read" - "because I don\'t.', 'No mainstream media can be trusted?', "Don't listen to the mainstream media."] | G58: Distrust in Mainstream Media | I58: 3-Oon after-Behavior/action
A59: 58 | B59: 134 | C59: 192 | D59: 134_talk anymore_speak anymore_even talk_avoiding | E59: ['talk anymore', 'speak anymore', 'even talk', 'avoiding', 'talk really', 'talk know', 'talk anything', 'interacting', 'really nothing', 'able talk'] | F59: ['I cant talk to any of them anymore.', 'None of them will speak to me anymore.', 'I hardly speak to them anymore.', 'I don‚Äôt speak with them anymore.', "And I can't take being in the same room as them when they talk about it anymore."] | G59: Family Communication Breakdown Due to QAnon | I59: 3-Oon after-Impact to narr
A60: 59 | B60: 135 | C60: 191 | D60: 135_fox_tucker_fox news_carlson | E60: ['fox', 'tucker', 'fox news', 'carlson', 'tucker carlson', 'alex jones', 'alex', 'jones', 'newsmax', 'watches'] | F60: ["The only thing she even watches is Fox News and she's a HUGE fan of Tucker Carlson, but I imagine she follows up with a bunch of crazy nonsense on Facebook.", 'Showed her Tucker Carlson specials.', 'She watches Tucker Carlson and the Five, and sometimes just watches Fox all day.', 'She actually didn‚Äôt watch Fox News for some time after they booted Tucker Carlson but she is watching and listening to Fox News now.', 'She sent several Fox News videos of Tucker Carlson, Sean Hannity, and Laura Ingraham.'] | G60: Influence of Fox News and Tucker Carlson on QAnon Beliefs | I60: 2-Trigger-Influencers
A61: 60 | B61: 143 | C61: 185 | D61: 143_nightmare_sleep_dream_nightmares | E61: ['nightmare', 'sleep', 'dream', 'nightmares', 'sleeping', 'wake', 'dreams', 'schedule', 'bed', 'nights'] | F61: ['I just want to wake up from this nightmare.', 'Then my worst nightmare happened.', 'The whole Damar Hamlin story was a nightmare in my house.', 'EDIT: This is my worst nightmare.', 'This nightmare has been going on for nearly a year and I lose sleep nightly over it.'] | G61: Family Distress Over QAnon Involvement | J61: Narr's feeling
A62: 61 | B62: 144 | C62: 182 | D62: 144_cancer_diagnosed_stage_cure cancer | E62: ['cancer', 'diagnosed', 'stage', 'cure cancer', 'treatment', 'lung', '26', 'cure', 'survivor', 'passed away'] | F62: ['Mom is at risk with having had cancer.', "Even if cancer risk wasn't part of the equation, we need sunscreen.", 'So some years ago I was in the hospital with cancer.', 'You brought this cancer into our home.', "So my sister's friend has breast cancer."] | G62: Cancer and Health Concerns | I62: 0-Background-Health
A63: 62 | B63: 145 | C63: 182 | D63: 145_live life_take care_back normal_go back normal | E63: ['live life', 'take care', 'back normal', 'go back normal', 'normal life', 'normalcy', 'let live', 'want live', 'life want', 'normal people'] | F63: ['Take care of yourself, everyone.', 'Try to live your life instead and become the person you want to be.', 'I just want to live my life.', 'I hope all our loved ones can go back to more of a normal soon.', 'I just want everything to go back to normal.'] | G63: Desire for Normalcy and Personal Well-being | J63: Narr's feeling
A64: 63 | B64: 146 | C64: 181 | D64: 146_elected_season_2020 election_got elected | E64: ['elected', 'season', '2020 election', 'got elected', 'got worse', 'gotten worse', 'trump got elected', 'presidential election', '2016 election', '2016'] | F64: ['Fast forward to the 2016 election.', 'Even all of those years ago when Trump got elected, you could just feel like something bigger was coming down the line.', "It's gotten way worse since Trump got elected.", 'but when trump got elected it just got so much worse.', 'Sometime after Trump got elected, everything got worse.'] | G64: Impact of Trump's Election on QAnon Beliefs | I64: 2-Trigger-Election
A65: 64 | B65: 151 | C65: 172 | D65: 151_fight_fights_fighting_fought | E65: ['fight', 'fights', 'fighting', 'fought', 'got fight', 'want fight', 'tension', 'huge fight', 'big fight', 'fighting back'] | F65: ['Especially when that fight will do absolutely no good.', "I was so sick, I didn't have the fight in me to do anything but hear what was going on and wish it wasn't.", "I didn't talk back and I didn't fight.", 'Maybe 2 months after this fight the videos start back up.', 'as a means to not start a fight.'] | G65: Family Conflict Over QAnon Beliefs | H65: Narrator stops fighting | I65: 3-Oon after-Impact to narr
A66: 65 | B66: 153 | C66: 169 | D66: 153_bipolar_mental illness_illness_disorder | E66: ['bipolar', 'mental illness', 'illness', 'disorder', 'mentally ill', 'psych', 'mental health', 'mentally', 'psychiatrist', 'ill'] | F66: ["She doesn't believe in mental illness, because she isn't well.", 'A few things about her: \n- Her mother had bipolar issues and she almost certainly suffers from some sort of mental illness, depression has been an issue for her in the past.', 'I also believe that she has undiagnosed bipolar disorder or borderline personality disorder.', "Despite being diagnosed as bipolar, she says she's not now.", 'The doctors have tried different medication ‚Äúcocktails.‚Äù She is suffering from depression, anxiety and was diagnosed with bipolar disorder at a psych ward.'] | G66: Mental Health and QAnon Involvement | H66: Mental Health Issues from Qanon Believers | I66: 0-Background-Mental State
A67: 157 | B67: 419 | C67: 167 | D67: 156_empathy_compassion_compassionate_empathetic | E67: ['empathy', 'compassion', 'compassionate', 'empathetic', 'empathize', 'nice', 'kindness', 'understanding', 'lack', 'sympathy'] | F67: ['He does not show compassion love or empathy and that is my fault he says.', 'love and compassion and empathy for fucking everyone.', 'But, with what he says and does I just can‚Äôt have any compassion or empathy for him at this point.'] | G67: Loss of Compassion and Empathy in Loved Ones | I67: 3-Oon after-Behavior/action
A68: 66 | B68: 155 | C68: 168 | D68: 155_mental health_toll_taking toll_mental health issues | E68: ['mental health', 'toll', 'taking toll', 'mental health issues', 'mental illness', 'affecting', 'illness', 'professional', 'depression', 'health issues'] | F68: ["Because this isn't good for my mental health.", "Ruminating on it hasn't been good for my mental health.", 'That will help my mental health!', 'How does anyone deal with this while not compromising their mental health?', 'I had to for my own mental health.'] | G68: Impact of QAnon on Mental Health | H68: (Negative) Impact? | I68: 3-Oon after-Impact to narr
A69: 67 | B69: 157 | C69: 164 | D69: 157_anger_emotions_rage_sadness | E69: ['anger', 'emotions', 'rage', 'sadness', 'angry time', 'frustration', 'emotion', 'angry sad', 'consuming', 'describe'] | F69: ["But getting my emotions to fall in line with that, just isn't possible.", 'There‚Äôs just so many emotions about all this.', "If I'm angry at someone the anger never lasts long.", 'What do I do about this anger?', 'I stewed in the anger for about a day.'] | G69: Emotional Struggles with Anger | I69: 3-Oon after-Impact to narr | J69: Narr's feeling
A70: 68 | B70: 158 | C70: 160 | D70: 158_shocked_surprised_shock_disappointed | E70: ['shocked', 'surprised', 'shock', 'disappointed', 'surprise', 'shocking', 'surprising', 'stunned', 'say least', 'omg'] | F70: ['I‚Äôm just so shocked and disappointed.', 'I was disappointed, but not shocked.', 'I‚Äôm so shocked and disappointed and...worried.', 'I was shocked, and pleasantly surprised.', 'He was surprised, but not shocked.'] | G70: Emotional Reactions to QAnon Involvement | H70: (shock and disappointment) | I70: 3-Oon after-Impact to narr
A71: 69 | B71: 160 | C71: 156 | D71: 160_still love_want around_love much_want life | E71: ['still love', 'want around', 'love much', 'want life', 'get back', 'love lot', 'much miss', 'love even', 'love like', 'around like'] | F71: ['I barely want to be around them lately and it‚Äôs honestly sad.', 'I don‚Äôt want to be around them, like at all.', 'I don‚Äôt want to be around them and I don‚Äôt want them in my life.', 'We still love them though.', 'I still love them though.'] | G71: Strained Family Relationships Due to QAnon Involvement | H71: Narrator not wanting to be around Q people (but conflicted) | I71: 3-Oon after-Impact to narr
A72: 70 | B72: 161 | C72: 155 | D72: 161_evidence_misinformation_proof_claims | E72: ['evidence', 'misinformation', 'proof', 'claims', 'sources', 'proven', 'proven wrong', 'claim', 'facts', 'prove'] | F72: ['It was about the misinformation.', 'What is anecdotal evidence and what makes this type of evidence weak?', "But there's absolutely *no* evidence at all to support this claim.", 'Evidence doesn‚Äôt seem to do much.', "It, doesn't matter what my evidence was or where it came from."] | G72: Challenges of Debunking Misinformation | H72: Challenges of Resistance to | I72: 3-Oon after-Behavior/action
A73: 71 | B73: 163 | C73: 154 | D73: 163_optimistic_hopeful_hope best_think hope | E73: ['optimistic', 'hopeful', 'hope best', 'think hope', 'hopefully', 'hope right', 'much hope', 'chance', 'like best', 'still hope'] | F73: ['It might just be my hopeful thinking.', 'I am hopefully but not sadly not optimistic.', "I guess for now, I'm cautiously optimistic.", 'I need some hope but I am not optimistic.', 'We have to remain optimistic and hopeful.'] | G73: Cautious Optimism and Hope | J73: Narr's feeling
A74: 72 | B74: 164 | C74: 154 | D74: 164_gold_silver_currency_bank | E74: ['gold', 'silver', 'currency', 'bank', 'banks', 'buying', 'crypto', 'market', 'collapse', 'dollars'] | F74: ["She's been buying little tiny gold bars off the internet for a few years now with her savings and getting silver from a local coin dealer...", "She said she's 'excited' for the days to come, because the Vatican has been raided and all the gold has been captured and America will no longer be on a system of currency, but live on a system of gold.", 'She has also spent over 1k on buying silver after these qanon group chats said silver would be worth far more than gold.', 'She dragged me to the gold and silver store that featured ACTUAL SILVER COINS WITH HIS FUCKING HEAD ON THEM.', "Because of this, she's convinced gold and silver will take over as the primary currencies of the world."] | G74: Precious Metals Investment Beliefs in QAnon | I74: 3-Oon after-Behavior/action
A75: 73 | B75: 169 | C75: 152 | D75: 169_communist_communism_socialist_socialism | E75: ['communist', 'communism', 'socialist', 'socialism', 'communists', 'revolution', 'democratic', 'democrat', 'america', 'labeled'] | F75: ["That's what communism is now?", 'He just talked to me for 3 hours about communism and the above.', 'So they hate communism right?', 'Your belief and your hate for Trump or enough for you to watch your Country turn socialist and then communist as every country in the world that was ever socialist resulted in communism and watch your family go to concentration camps for their beliefs and not vaccination which are now bio weapons.', 'Socialism = Communism and Capitalism is the only way.'] | G75: Fear of Communism and Socialism | H75: Fear of Criticism towards | I75: 3-Oon after-Belief
A76: 74 | B76: 172 | C76: 142 | D76: 172_food_water_hoarding_stock | E76: ['food', 'water', 'hoarding', 'stock', 'canned', 'prepper', 'foods', 'prepping', 'stocking', 'supplies'] | F76: ['My conspiritual mother has been begging me to stock up on water, candles, blankets and canned food because this winter it is going to go down.', 'They are also hoarding canned foods and water which they consider "prepping".', 'Stock up on food and water.', 'Dehydrated food, flashlights and radios and chargers.', "I'm not the one who is storing food."] | G76: Prepping and Hoarding Supplies | I76: 3-Oon after-Behavior/action
A77: 75 | B77: 173 | C77: 140 | D77: 173_exhausted_tired_numb_emotionally | E77: ['exhausted', 'tired', 'numb', 'emotionally', 'drained', 'sick tired', 'mentally', 'fatigue', 'depressed', 'whole thing'] | F77: ['I‚Äôm exhausted from it all.', "I'm so exhausted from the mental gymnastics.", "I'm exhausted, what can I do?", 'So exhausted but almost there.', 'I am so exhausted and tired.'] | G77: Emotional Exhaustion from QAnon Involvement | I77: 3-Oon after-Impact to narr
A78: 76 | B78: 174 | C78: 140 | D78: 174_cat_cats_boxes_schools | E78: ['cat', 'cats', 'boxes', 'schools', 'identify', 'animals', 'station', 'come get', 'dogs', 'identifying'] | F78: ['We were talking about his cat.', 'I told him on the phone I had to get our cat put down today.', "Those lilies can't be out where the cat will get to them.", 'Not so much the cat though.', "They have a cat, so I told my mother that lilies are highly toxic to cats and she can't have the lilies where the cat will get to them."] | G78: Pet Safety Concerns Regarding Cats | H78: ??? | I78: ???
A79: 77 | B79: 175 | C79: 139 | D79: 175_pandemic_pandemic started_since pandemic_plandemic | E79: ['pandemic', 'pandemic started', 'since pandemic', 'plandemic', 'beginning pandemic', 'pandemic hit', 'ever since', 'beginning', 'went deep', 'start pandemic'] | F79: ['She always tells me this pandemic is all about the money.', 'She still calls the pandemic the "scamdemic."', 'And she calls the pandemic a "pland-emic".', 'It seemed that as the pandemic were on, she became more and more cemented in her views.', 'But the pandemic changed her.'] | G79: Pandemic Conspiracy Beliefs | I79: 3-Oon after-Belief
A80: 78 | B80: 176 | C80: 139 | D80: 176_live parents_still live_still living_financially | E80: ['live parents', 'still live', 'still living', 'financially', 'financial', 'parents since', '34', 'financially dependent', 'parents brother', 'dependent'] | F80: ['Still live with my parents because housing prices are insane.', 'My son and I live with my parents.', "I'm F21 and still live with my parents unfortunately.", 'I still live with my parents.', 'I still live with my parents due to money issues.'] | G80: Adult Children Living with Parents Due to Financial Constraints | I80: 0-Background-Living condition
A81: 79 | B81: 177 | C81: 138 | D81: 177_book_books_author_recommend | E81: ['book', 'books', 'author', 'recommend', 'guide', 'published', 'chapter', 'library', 'though family', 'shop'] | F81: ['I‚Äôd like to bring it forth as a book to recommend to everyone in this subreddit, as I found that the list of resources/books did not include this one book specifically.', "I've tried reading the book and listening to the audiobook, but it's just so long.", 'Oh, it‚Äôs in the book.', 'There was always a new book to read.', 'That could be a book in and of itself.'] | G81: Books and Recommendations in QAnon Context
A82: 80 | B82: 178 | C82: 137 | D82: 178_5g_towers_radiation_cell | E82: ['5g', 'towers', 'radiation', 'cell', 'bill gates', 'gates', 'phones', 'bill', 'brains', 'rubbish'] | F82: ['She talks about 5g being dangerous.', 'Then he goes on to tell us how 5G is melting her brain and other crap.', '5G is bad and they will control all of you.', 'Is that a 5g thing?', 'It all started with 5G.'] | G82: 5G Conspiracy Theories | I82: 3-Oon after-Belief
A83: 180 | B83: 179 | C83: 137 | D83: 179_addiction_addict_addicted_drug | E83: ['addiction', 'addict', 'addicted', 'drug', 'addictive', 'drugs', 'recovering', 'someone love', 'like watching', 'loved one'] | F83: ["I know about addiction, I'm a recovering addict but this is way way over my head.", 'This is no worse than a drug addiction.', "It's almost an addiction in and of itself."] | G83: Addiction-like Behavior in QAnon Belief | J83: Perception of Q
A84: 81 | B84: 181 | C84: 136 | D84: 181_14_18_minor_33 | E84: ['14', '18', 'minor', '33', '30s', '16', '40s', '20s', 'years old', 'thirties'] | F84: ['They said that I\'m "their minor," so I (and my body, I assume) am theirs until I\'m 18.', 'So now, despite the fact that I‚Äôm in my early 20s and can barely keep myself afloat, I‚Äôm now taking care of a 16 year old girl.', "I'm 14 now, obviously, almost 15.", 'i was about 16-18 for all of this.', "**Edit:** Yes, I'm still a minor, but I turn 18 in less than a month."] | G84: Family Dynamics and Responsibilities Involving Minors
A85: 82 | B85: 182 | C85: 136 | D85: 182_pandemic_since pandemic_beginning pandemic_pandemic started | E85: ['pandemic', 'since pandemic', 'beginning pandemic', 'pandemic started', 'beginning', 'pandemic hit', 'pre', 'pandemic began', 'move back', 'start pandemic'] | F85: ["It's been a struggle since the pandemic started to keep a relationship with them, but pre-pandemic we were able to keep politics out and my son to have a great relationship with his grandpa.", 'My mom died at the beginning of the pandemic.', 'Thinking about leaving this family when this pandemic is over.', "My mom wasn't the same ever since the pandemic.", 'Before the pandemic, my mother moved in with me.'] | G85: Family Strain During Pandemic | I85: 2-Trigger-Pandemic
A86: 83 | B86: 183 | C86: 135 | D86: 183_freedom_war_constitution_freedoms | E86: ['freedom', 'war', 'constitution', 'freedoms', 'amendment', 'policy', 'federal government', 'governments', 'allies', 'constitutional'] | F86: ['They shriek about the constitution and how it‚Äôs in peril, yet are constitutionally illiterate.', "You think we're in a war?", 'We have to face the hate head on - and if that means war, it means war.', "That's the beauty of freedom and independence.", 'But without that unease, there is no freedom.'] | G86: Constitutional Concerns and Freedom Narratives | H86: ??? | I86: ???
A87: 84 | B87: 184 | C87: 134 | D87: 184_boundaries_boundary_setting_setting boundaries | E87: ['boundaries', 'boundary', 'setting', 'setting boundaries', 'set boundary', 'set boundaries', 'respect boundaries', 'firm', 'respected', 'respect'] | F87: ['Because they do not understand boundaries.', "The boundaries aren't working so....", 'And if they have any issue on my boundaries that I will set, that we will have a problem.', "I guess boundaries don't really mean anything to these people.", 'Do my boundaries seem okay?'] | G87: Boundary Challenges in QAnon Relationships | I87: 3-Oon after-Behavior/action
A88: 85 | B88: 186 | C88: 134 | D88: 186_believes things_believe things_want believe_told believe | E88: ['believes things', 'believe things', 'want believe', 'told believe', 'believe stuff', 'even said', 'still believes', 'believe told', 'saying believe', 'know believes'] | F88: ['She believes these things without question.', "And it's from the same woman that somehow believes all these things simultaneously somehow.", 'She believes some of the things but not all of them.', 'I‚Äôm literally astonished she believes these things.', 'She believes in those things... Out of desperation.'] | G88: Unwavering Belief in Conspiracy Narratives | I88: 3-Oon after-Behavior/action
A89: 87 | B89: 189 | C89: 131 | D89: 189_lizard_lizard people_clones_clone | E89: ['lizard', 'lizard people', 'clones', 'clone', 'queen', 'earth', 'aliens', 'people real', 'clinton', 'executed'] | F89: ['They are clones or lizard people.', 'And there are lizard people!', 'lizard people who are -- there, for some reason?', 'That they are lizard people or working with the lizard people.', '(Where are the lizard people pics?)'] | G89: Belief in Lizard People Conspiracy | I89: 3-Oon after-Belief
A90: 88 | B90: 191 | C90: 131 | D90: 191_go contact_cut contact_low contact_cutting contact | E90: ['go contact', 'cut contact', 'low contact', 'cutting contact', 'went contact', 'low', 'contact since', 'limited contact', 'gone contact', 'going contact'] | F90: ['I cannot cut contact but the contact to them is not good for me.', 'Is there a way to have a relationship, or do I need to cut contact?', 'For these reasons we are low contact not no contact.', "I'm not at a place where I want to go no-contact.", 'Did you go no contact?'] | G90: Managing Contact with QAnon-Influenced Relatives | H90: …no/low Contact... | I90: 3-Oon after-Impact to narr
A91: 89 | B91: 192 | C91: 129 | D91: 192_decision_options_choice_right decision | E91: ['decision', 'options', 'choice', 'right decision', 'made right', 'make decision', 'dilemma', 'option', 'weighing', 'decisions'] | F91: ["I'm sorry if I made the wrong decision.", 'It was/is a hard decision to make.', "And I hope I didn't make the wrong decision.", 'This was probably a good decision.', 'It is the principled decision.'] | G91: Decision-Making Dilemmas | J91: Narr's feeling
A92: 90 | B92: 194 | C92: 127 | D92: 194_heart goes_breaks_breaks heart_broken | E92: ['heart goes', 'breaks', 'breaks heart', 'broken', 'heart breaks', 'heart breaking', 'breaking heart', 'broke heart', 'breaking', 'hearts'] | F92: ['The thought breaks my heart.', 'It breaks my heart that this is happening.', 'It really breaks my heart, man.', 'Now, that breaks my heart!', 'it breaks my heart that this was too much to ask for.'] | G92: Heartbreak Over Family Involvement in QAnon | I92: 3-Oon after-Impact to narr
A93: 91 | B93: 196 | C93: 126 | D93: 196_jfk_jr_jfk jr_alive | E93: ['jfk', 'jr', 'jfk jr', 'alive', 'still alive', 'kennedy', 'michael', 'assassination', 'john', 'dead'] | F93: ['The whole JFK JR being alive too... (And a republican!?', '"Have you heard of JFK Jr?"', 'Some nonsense about JFK Jr being Q himself.', 'What is their fascination with JFK Jr?', 'He believes that JFK Jr. is alive.'] | G93: Belief in JFK Jr. Being Alive | I93: 3-Oon after-Belief
A94: 92 | B94: 197 | C94: 125 | D94: 197_kamala_kamala harris_harris_wins | E94: ['kamala', 'kamala harris', 'harris', 'wins', 'vote', 'win', 'voted', 'voting', 'biden', 'president'] | F94: ['I want Kamala to win, but I‚Äôll never hear the end of it from my parents if she does.', 'I didn‚Äôt mention the republicans who have endorsed Kamala Harris.', 'Until tonight, when my father brought up Kamala Harris.', '**\xa0\xa0\xa0**He is the husband of KAMALA HARRIS!', 'She called Kamala Harris ‚Äústupid‚Äù.'] | G94: Family Reactions to Kamala Harris and 2020 Election | I94: 3-Oon after-Belief
A95: 93 | B95: 198 | C95: 125 | D95: 198_autistic_autism_diagnosed_spectrum | E95: ['autistic', 'autism', 'diagnosed', 'spectrum', 'functioning', 'undiagnosed', 'severe', 'syndrome', 'adhd', 'affects'] | F95: ['My partner, as I‚Äôve mentioned, is autistic.', 'As I just mentioned, my daughter is autistic.', 'Two of them are autistic (I am too by the way - it seems to be hereditary).', 'Even being autistic i can read that face.', 'he does not know i‚Äôm autistic.'] | G95: Autism and QAnon Involvement | J95: narr+others
A96: 94 | B96: 199 | C96: 125 | D96: 199_adrenochrome_blood_drink_drink blood | E96: ['adrenochrome', 'blood', 'drink', 'drink blood', 'harvesting', 'harvest', 'blood libel', 'libel', 'children blood', 'elite'] | F96: ['&#x200B;\n\nQuestion 2: Where is this Adrenochrome business coming from?', 'Then the adrenochrome stories started.', 'I asked them if they knew what adrenochrome was.', 'Even the whole adrenochrome crap.', 'The whole adrenochrome thing still real.'] | G96: Adrenochrome Conspiracy Beliefs | I96: 3-Oon after-Belief
A97: 95 | B97: 200 | C97: 123 | D97: 200_arrested_arrests_jail_trial | E97: ['arrested', 'arrests', 'jail', 'trial', 'crimes', 'criminal', 'charges', 'convicted', 'arrest', 'possession'] | F97: ["That there's going to be mass arrests.", 'I can‚Äôt wait until all these stupid people are arrested.', 'I think he got reckless as he got arrested but was let out awaiting trial.', 'He was arrested by the cops and taken to jail, but was released shortly after.', 'He believes some have been in jail for years with no trial.'] | G97: Legal Consequences of QAnon Involvement | I97: 3-Oon after-Legal
A98: 96 | B98: 202 | C98: 121 | D98: 202_divorce_filed_divorced_married | E98: ['divorce', 'filed', 'divorced', 'married', 'marriage', 'divorcing', 'option', 'papers', 'separated', 'signed'] | F98: ['I don‚Äôt know if this is divorce worthy.', 'They didn‚Äôt divorce, but didn‚Äôt see each other often.', 'In the end, it didn‚Äôt weigh in at all around the divorce.', 'Divorce was brought up by me in the conversation.', 'I am the one who asked for the divorce.'] | G98: Marital Strain Due to QAnon Involvement | I98: 3-Oon after-Social
A99: 97 | B99: 203 | C99: 121 | D99: 203_realities_alternate_alternate reality_two different | E99: ['realities', 'alternate', 'alternate reality', 'two different', 'separate', 'totally different', 'like two', 'bye', 'shifting', 'touch reality'] | F99: ['We truly live two different realities.', '), inside jobs everywhere, alternate realities, ... you guys know.', 'It‚Äôs like we live in two differet realities with no way to reach the other side.', "I'm just afraid that our realities are no longer congruent, and where can any couple go from there?", 'These things are two separate alternate realities.'] | G99: Divergent Realities in Relationships | I99: ??? | J99: Narr's feeling
A100: 98 | B100: 205 | C100: 120 | D100: 205_personality_lost mind_bitter_gotten much worse | E100: ['personality', 'lost mind', 'bitter', 'gotten much worse', 'gotten much', 'temper', 'much worse', 'erratic', 'gotten worse', 'big part'] | F100: ["It just doesn't fit his personality.", 'It was a part of his personality.', 'He has to make it his personality.', 'Little by little his personality changed.', 'Is this just his personality now?'] | G100: Personality Changes Due to QAnon Involvement | I100: 3-Oon after-Behavior/action
...

Sheet prelim_categories
A1: {=_xlfn._xlws.SORT(_xlfn.UNIQUE(topics_merged!I3:I264))} -> ??? | C1: =COUNTIF(topics_merged!I$3:I$264, A1) -> 15
A2: 0-Background-Addiction | C2: =COUNTIF(topics_merged!I$3:I$264, A2) -> 1 | D2: =SUM(C2:C21) -> 30
A3: 0-Background-Age | C3: =COUNTIF(topics_merged!I$3:I$264, A3) -> 1
A4: 0-Background-Closeness | C4: =COUNTIF(topics_merged!I$3:I$264, A4) -> 1
A5: 0-Background-Education | C5: =COUNTIF(topics_merged!I$3:I$264, A5) -> 1
A6: 0-Background-Family | C6: =COUNTIF(topics_merged!I$3:I$264, A6) -> 3
A7: 0-Background-Generation | C7: =COUNTIF(topics_merged!I$3:I$264, A7) -> 1
A8: 0-Background-Geography | C8: =COUNTIF(topics_merged!I$3:I$264, A8) -> 2
A9: 0-Background-Health | C9: =COUNTIF(topics_merged!I$3:I$264, A9) -> 2
A10: 0-Background-Housing | C10: =COUNTIF(topics_merged!I$3:I$264, A10) -> 1
A11: 0-Background-Ideology | C11: =COUNTIF(topics_merged!I$3:I$264, A11) -> 2
A12: 0-Background-Job | C12: =COUNTIF(topics_merged!I$3:I$264, A12) -> 1
A13: 0-Background-Living condition | C13: =COUNTIF(topics_merged!I$3:I$264, A13) -> 1
A14: 0-Background-Mental State | C14: =COUNTIF(topics_merged!I$3:I$264, A14) -> 1
... A21: 0-Background-Substance Use | C21: =COUNTIF(topics_merged!I$3:I$264, A21) -> 1
A22: 1-Oon before-Personality | C22: =COUNTIF(topics_merged!I$3:I$264, A22) -> 2 | D22: 2
A23: 2-Trigger-Alt news | C23: =COUNTIF(topics_merged!I$3:I$264, A23) -> 1 | D23: =SUM(C23:C29) -> 16
A24: 2-Trigger-Election | C24: =COUNTIF(topics_merged!I$3:I$264, A24) -> 1
A25: 2-Trigger-Influencers | C25: =COUNTIF(topics_merged!I$3:I$264, A25) -> 2
A26: 2-Trigger-Lockdown | C26: =COUNTIF(topics_merged!I$3:I$264, A26) -> 1
A27: 2-Trigger-Pandemic | C27: =COUNTIF(topics_merged!I$3:I$264, A27) -> 3
A28: 2-Trigger-Religion | C28: =COUNTIF(topics_merged!I$3:I$264, A28) -> 1
A29: 2-Trigger-Social Media | C29: =COUNTIF(topics_merged!I$3:I$264, A29) -> 7
A30: 3-Oon after-Behavior/action | B30: Behavior or Action of Object of Narration i.e Q person (things that they actually do/did) | C30: =COUNTIF(topics_merged!I$3:I$264, A30) -> 45 | D30: =SUM(C30:C38) -> 156
A31: 3-Oon after-Belief | B31: Beliefs of Object of Narration i.e Q person (things that they believe in, not necessary enforce(?) themselves) | C31: =COUNTIF(topics_merged!I$3:I$264, A31) -> 47
A32: 3-Oon after-Family | C32: =COUNTIF(topics_merged!I$3:I$264, A32) -> 1
A33: 3-Oon after-Impact to narr | C33: =COUNTIF(topics_merged!I$3:I$264, A33) -> 35
A34: 3-Oon after-Impact to others | C34: =COUNTIF(topics_merged!I$3:I$264, A34) -> 9
A35: 3-Oon after-Job | C35: =COUNTIF(topics_merged!I$3:I$264, A35) -> 1
A36: 3-Oon after-Legal | C36: =COUNTIF(topics_merged!I$3:I$264, A36) -> 1
A37: 3-Oon after-Social | C37: =COUNTIF(topics_merged!I$3:I$264, A37) -> 14
A38: 3-Oon after-State | C38: =COUNTIF(topics_merged!I$3:I$264, A38) -> 3
A39: 0 | C39: =COUNTIF(topics_merged!I41:I302, A39) -> 0

Sheet random_sample
B1: Topic | C1: Count | D1: Name | E1: Representation | F1: Representative_Docs | G1: GPT Label | H1: Better Label? | I1: Category (0 - Background, 1 - Oon before, 2 - Trigger, 3 - Oon after)
A2: 7 | B2: 31 | C2: 618 | D2: 31_drops_believer_related_full blown | E2: ['drops', 'believer', 'related', 'full blown', 'blown', 'er', 'followers', 'anonymous', 'believers', 'discovered'] | F2: ['He is a stout Q believer.', "I look through his posts, he's full blown Q guy, Trump is the savior, the whole thing.", 'He pretty quickly became a full blown q convert and stopped going into work more and more often so he could spend more time watching youtube and talking to other fellow believers.', 'Sorry for the rant..... anyway......\n\nNot only was everyone I was watching talking about "Q Drops"...but they were also all becoming..............extremely fond of Trump.', 'he calls Q drops and the videos from top Q believers on youtube the "new Bible" and tells me to throw my copies of the "old" one away.'] | G2: QAnon Belief and Influence on Personal Lives | H2: Full-blown stage into Q?
A3: 10 | B3: 39 | C3: 523 | D3: 39_insanity_crazy one_madness_sane | E3: ['insanity', 'crazy one', 'madness', 'sane', 'sanity', 'craziness', 'like crazy', 'think crazy', 'going crazy', 'going insane'] | F3: ['I feel like I‚Äôm the crazy one.', "I don't think I have it in me to deal with any more of this insanity.", 'The man lost *everything* to this insanity.', "I'm so sick of the insanity.", 'When does this insanity end?'] | G3: Family Struggles with QAnon-Induced Insanity | H3: Family Struggles with
A4: 26 | B4: 64 | C4: 363 | D4: 64_older brother_brothers_older_younger brother | E4: ['older brother', 'brothers', 'older', 'younger brother', 'brother said', 'like brother', 'little brother', 'younger', 'brother told', 'lose'] | F4: ['My older brother has always walked on water in my eyes.', "I MISS MY OLDER BROTHER WHO I WISHED TO BE AS COOL AS GROWING UP BUT NOW I DON'T EVEN RECOGNIZE YOU.", 'My brothers are the same.', 'Both of my brothers have done this, it‚Äôs my turn.', 'My older brother was so special to us (lost him \\~7 years ago).'] | G4: Family Strain Due to QAnon Beliefs | H4: [Oon-Narrator) Relationship - Brother | I4: 0-Background-Relationship with narr
A5: 37 | B5: 92 | C5: 276 | D5: 92_red_texas_florida_area | E5: ['red', 'texas', 'florida', 'area', 'rural', 'town', 'county', 'city', 'states', 'blue'] | F5: ['We live in a red state.', "We're also in a red state.", 'Still, he is deep in a red state.', 'We are from a very small rural red town.', 'I live in a very red area.'] | G5: Impact of QAnon in Conservative Rural Areas | H5: Demographics (red state) | I5: 0-Background-Political region
A6: 47 | B6: 114 | C6: 226 | D6: 114_siblings_cousin_cousins_sibling | E6: ['siblings', 'cousin', 'cousins', 'sibling', 'aunts', 'uncle', 'older', 'aunt', 'aunt uncle', 'brothers'] | F6: ['I have many other siblings.', 'And I‚Äôm their only child, no siblings.', "Me and my siblings don't know what to do.", 'I just sorry for my siblings', 'My cousins were like siblings.'] | G6: Family Relationships and QAnon Impact | H6: [Oon-Narrator) Relationship - Siblings | I6: 0-Background-Relationship with narr
A7: 57 | B7: 133 | C7: 192 | D7: 133_journalists_fake news_mainstream_mainstream media | E7: ['journalists', 'fake news', 'mainstream', 'mainstream media', 'news sources', 'bias', 'fake', 'sources', 'outlets', 'journalism'] | F7: ['It\'s all "fake news".... ... ... ... ... ... ... ... really?', 'I understand mainstream media is not perfect and of course they have their own bias they make mistakes they even lie sometimes but atleast I know there mostly credible, studied journalists and don‚Äôt want to ruin reputation.', '"How can you know when you only read "fake news" and the mainstream media and what "they" want you to read" - "because I don\'t.', 'No mainstream media can be trusted?', "Don't listen to the mainstream media."] | G7: Distrust in Mainstream Media | I7: 3-Oon after-Behavior/action
A8: 65 | B8: 153 | C8: 169 | D8: 153_bipolar_mental illness_illness_disorder | E8: ['bipolar', 'mental illness', 'illness', 'disorder', 'mentally ill', 'psych', 'mental health', 'mentally', 'psychiatrist', 'ill'] | F8: ["She doesn't believe in mental illness, because she isn't well.", 'A few things about her: \n- Her mother had bipolar issues and she almost certainly suffers from some sort of mental illness, depression has been an issue for her in the past.', 'I also believe that she has undiagnosed bipolar disorder or borderline personality disorder.', "Despite being diagnosed as bipolar, she says she's not now.", 'The doctors have tried different medication ‚Äúcocktails.‚Äù She is suffering from depression, anxiety and was diagnosed with bipolar disorder at a psych ward.'] | G8: Mental Health and QAnon Involvement | H8: Mental Health Issues of Qanon Believers | I8: 0-Background-Mental State
A9: 66 | B9: 155 | C9: 168 | D9: 155_mental health_toll_taking toll_mental health issues | E9: ['mental health', 'toll', 'taking toll', 'mental health issues', 'mental illness', 'affecting', 'illness', 'professional', 'depression', 'health issues'] | F9: ["Because this isn't good for my mental health.", "Ruminating on it hasn't been good for my mental health.", 'That will help my mental health!', 'How does anyone deal with this while not compromising their mental health?', 'I had to for my own mental health.'] | G9: Impact of QAnon on Mental Health | H9: (Negative) Impact? | I9: 3-Oon after-Impact to narr
A10: 78 | B10: 176 | C10: 139 | D10: 176_live parents_still live_still living_financially | E10: ['live parents', 'still live', 'still living', 'financially', 'financial', 'parents since', '34', 'financially dependent', 'parents brother', 'dependent'] | F10: ['Still live with my parents because housing prices are insane.', 'My son and I live with my parents.', "I'm F21 and still live with my parents unfortunately.", 'I still live with my parents.', 'I still live with my parents due to money issues.'] | G10: Adult Children Living with Parents Due to Financial Constraints | I10: 0-Background-Living condition
A11: 97 | B11: 203 | C11: 121 | D11: 203_realities_alternate_alternate reality_two different | E11: ['realities', 'alternate', 'alternate reality', 'two different', 'separate', 'totally different', 'like two', 'bye', 'shifting', 'touch reality'] | F11: ['We truly live two different realities.', '), inside jobs everywhere, alternate realities, ... you guys know.', 'It‚Äôs like we live in two differet realities with no way to reach the other side.', "I'm just afraid that our realities are no longer congruent, and where can any couple go from there?", 'These things are two separate alternate realities.'] | G11: Divergent Realities in Relationships | I11: 3-Oon after-Impact to narr
A12: 108 | B12: 228 | C12: 109 | D12: 228_science_scientific_scientist_scientists | E12: ['science', 'scientific', 'scientist', 'scientists', 'trust', 'peer', 'studies', 'data', 'facebook youtube', 'anti science'] | F12: ['I renounce science, I‚Äôll renounce it all I fucking want, it‚Äôs not real!', 'I will never question science again.', 'I don‚Äôt believe in science, it‚Äôs not real!', 'Put that delicious science in my bodyyyyyy.', 'I talked them through all the science.'] | G12: Distrust in Science | I12: 3-Oon after-Beliefs
A13: 131 | B13: 272 | C13: 94 | D13: 272_nc_already gone_low contact_limited contact | E13: ['nc', 'already gone', 'low contact', 'limited contact', 'option', 'reasons', 'low', 'limited', 'reaching', 'november'] | F13: ['I am LC with them but cannog to NC,.', "I don't know how to be NC.", 'I had to go NC.', 'We went NC after that.', 'I‚Äôm going NC with my Q father.'] | G13: Navigating No Contact with QAnon Relatives | I13: 3-Oon after-Social
A14: 143 | B14: 295 | C14: 86 | D14: 295_tiktok_tik_tok_tik tok | E14: ['tiktok', 'tik', 'tok', 'tik tok', 'tiktoks', 'source information', 'teenagers', 'source', 'spend hours', 'dance'] | F14: ['https://vm.tiktok.com/ZMd4By9hV/\n\nMy other social media: www.linktr.ee/NathanTheCreator\n\nThank you.', 'can you send me LITERALLY any source other than tiktok and he can‚Äôt!!!!', 'I heard about this group from TikTok and I can‚Äôt believe how similar all these stories are to my friend.', 'Everything he knows is what my mom tells him from TikTok and FaceBook.', 'I don‚Äôt even HAVE tiktok.'] | G14: TikTok as a Source of Misinformation | I14: 2-Trigger-Social Media
A15: 162 | B15: 330 | C15: 74 | D15: 330_ages_two children_want kids_13 | E15: ['ages', 'two children', 'want kids', '13', 'two kids', 'beautiful', 'boys', '12', 'want children', '15'] | F15: ['I have two grandchildren, ages 13 and 15.', 'I have two kids, ages 11 and 12.', 'We have two children 15 and 13.', 'As I said, we have 8 kids, 4 boys (ages 24, 20, 13 and 11) and 4 girls (ages 23, 21, 17 and 15).', ' \nI (29F) am a live-in nanny, the family I nanny for has 6 kids: 3 girls (ages 15, 14, and 10) and 3 boys (ages 13, 12, and 8).'] | G15: Family Dynamics Involving Children and Teenagers | H15: Family Background? | I15: 0-Background-Family
A16: 169 | B16: 341 | C16: 71 | D16: 341_grey_grey rock_rock_gray | E16: ['grey', 'grey rock', 'rock', 'gray', 'method', 'setting boundaries', 'amp', 'afterwards', 'nc', 'yell'] | F16: ['And then the grey rock technique.', 'Why can‚Äôt I just grey rock?', 'Usually I grey rock it.', 'Grey Rock as best you can.', 'I wouldn‚Äôt call it grey rock either.'] | G16: Managing Interactions with QAnon Believers | H16: Dealing with Qs by disengaging | I16: 3-Oon after-Social
A17: 176 | B17: 354 | C17: 68 | D17: 354_uncle_cousin_uncles_hardly | E17: ['uncle', 'cousin', 'uncles', 'hardly', 'hitler', 'protests', 'aunt', 'grandpa', 'hardly ever', 'favorite'] | F17: ['With my uncle, I did the same.', 'Which is where my uncle comes in.', 'I have this uncle and when I was little he was just the funnest guy.', 'Why has my uncle gotten so crazy?', 'I love you Uncle Eddie ‚ù§Ô∏è'] | G17: Family Members Affected by QAnon | H17: (Narrator-oon) Relationship - Uncle | I17: 0-Background-Relationship with narr
A18: 179 | B18: 362 | C18: 66 | D18: 362_gets angry_anger_really angry_got angry | E18: ['gets angry', 'anger', 'really angry', 'got angry', 'mood', 'get angry', 'frustration', 'authorities', 'angry time', 'delusions'] | F18: ['In the latest series of texts, it is apparent that he was trying his best to hold back his obvious frustration, anger, and sadness.', 'He just gets more angry and pushes all your buttons.', '\\- He gets angry more easily in arguments, yelling and swearing more.', 'He gets angry if his knowledge is challenged.', 'His mood is very different and he gets more angry when we disagree on what is happening in the world.'] | G18: Increased Anger and Frustration in QAnon Believers | I18: 3-Oon after-Behavior/action
A19: 184 | B19: 371 | C19: 64 | D19: 371_boomers_boomer_generation_age | E19: ['boomers', 'boomer', 'generation', 'age', 'people age', 'aged', 'range', 'baby', 'homes', 'source'] | F19: ['My mom is a boomer.', 'Boomers were 19-37, parent age.', 'Q boomers are some very strange people.', 'In short I was basically like "lol, Boomers amiright??"', 'Which is stupid but whatever, boomers gonna boom.'] | G19: Boomer Generation and QAnon Involvement | I19: 0-Background-Generation
A20: 188 | B20: 382 | C20: 62 | D20: 382_days darkness_10 days_darkness_blackout | E20: ['days darkness', '10 days', 'darkness', 'blackout', 'grid', 'power grid', 'power', 'broadcast', 'shutting', 'ten'] | F20: ['Hiding purchases for when the 10 days of darkness would come.', 'The Instagram pictures were talking about the "10 Days of Darkness".', 'I asked him, whatever happened to the 10 days of darkness that you were so certain was going to happen?', '* How the "\\`10 days of darkness" is supposedly coming any time now.', "Yeah, ok. How's that 10 Days of Darkness going for y'all?"] | G20: QAnon "10 Days of Darkness" Belief | I20: 3-Oon after-Beliefs
A21: 196 | B21: 394 | C21: 60 | D21: 394_kool aid_kool_aid_koolaid | E21: ['kool aid', 'kool', 'aid', 'koolaid', 'drank', 'drinking', 'drink', 'quantum', 'drunk', 'one said'] | F21: ['The kool aid is strong.', "Somehow, he'd convinced her to drink the kool-aid.", 'The family that didn‚Äôt drink the kool aid and my friends that are basically family are all that I need.', 'AND they say I‚Äôm drinking the Kool-Aid?', "He's drank the Kool aid."] | G21: Family Impact of QAnon Beliefs | H21: Drink the Kool-aid = deep into something (bad) | I21: 3-Oon after-State
A22: 200 | B22: 398 | C22: 59 | D22: 398_leaning_right leaning_left leaning_always right | E22: ['leaning', 'right leaning', 'left leaning', 'always right', 'lean', 'leaned', 'left right', 'shifted', 'gotten older', 'dad always'] | F22: ['My father has always been right-leaning, and generally dismissive of most left-leaning ideas and concepts.', 'And my friend was always right-leaning.', 'I‚Äôm more centerish, left leaning now.', 'My dad was always right-leaning but my mom used to be left-leaning.', "I've always been left leaning and they've always been right leaning, but it's never been an issue."] | G22: Political Leaning Dynamics in Families | I22: 0-Background-Political leaning
A23: 204 | B23: 403 | C23: 58 | D23: 403_rush_limbaugh_rush limbaugh_radio | E23: ['rush', 'limbaugh', 'rush limbaugh', 'radio', 'listening', 'talk radio', 'every morning', 'fox', 'car', 'became thing'] | F23: ['I Despised Glenn Beck & rush Limbaugh, couldn‚Äôt even stand looking at them.', 'I started listening to Rush Limbaugh in 1997.', 'He was also my family‚Äôs new Rush Limbaugh.', 'He loved Rush Limbaugh and Glenn Beck and subsidiaries thereof.', 'You name it, he parroted it right out of a Rush Limbaugh segment.'] | G23: Influence of Rush Limbaugh on Family Dynamics | I23: 2-Trigger-Influencers
A24: 207 | B24: 411 | C24: 56 | D24: 411_dc_canada_communist_canadian | E24: ['dc', 'canada', 'communist', 'canadian', 'dictator', '6th', 'prime', 'prime minister', 'washington', 'dictatorship'] | F24: ['He texted me that Trudeau is using the pandemic to turn Canada fully communist.', 'We just got back from DC.', 'The ringleader tried to fly to DC on the 6th, for Christ‚Äôs sakes.', 'Is this going to be a big problem in DC that weekend?', 'My Qfriend who went to DC.'] | G24: QAnon Influence on Political Views and Events | H24: DC/Irrelevant | I24: 3-Oon after-Beliefs
A25: 209 | B25: 413 | C25: 56 | D25: 413_brushed_shrugged_nodded_like okay | E25: ['brushed', 'shrugged', 'nodded', 'like okay', 'huh', 'uh', 'hey', 'idea even', 'hmm', '48 hours'] | F25: ['Again, I brushed it off.', 'I still brushed it off.', 'Again, I just brushed it off.', 'The other just brushed it off.', 'I said no but you brushed it off.'] | G25: Dismissive Reactions to Concerns | I25: 3-Oon after-Social
A26: 211 | B26: 416 | C26: 56 | D26: 416_fauci_dr_wuhan_liar | E26: ['fauci', 'dr', 'wuhan', 'liar', 'traitor', 'lab', 'making money', 'agent', 'masks', 'funding'] | F26: ['anti mask and vaccine, believes Fauci is imprisoned for creating covid.', 'My mom told me in her uppity way that ‚ÄúThat Fauci is going to be in big trouble.', 'Fauci apparently tortured thousands of puppies with maggots....and is making trillions on the vaccine for a virus that HE created.', 'Then of course the whole Dr. Fauci created covid and wants to depopulate us with a vaccine thing.', 'Fauci is an older man.'] | G26: Dr. Fauci Conspiracy Theories | I26: 3-Oon after-Beliefs
A27: 224 | B27: 442 | C27: 52 | D27: 442_door_room_locked_opening | E27: ['door', 'room', 'locked', 'opening', 'closed', 'rooms', 'living room', 'bed', 'asleep', 'security'] | F27: ["I'm not opening up that door.", "I've finally closed the door.", "I've been keeping the door open (why?)", 'You open up the front door.', "‚òÖ‚òÖ‚òÖ\n\nI've left the door open."] | G27: Family Boundaries and Security Concerns
A28: 239 | B28: 18,93,310 | C28: 1245 | E28: ['covid', 'covid hoax', 'hoax', 'mask', 'masking', 'masks', 'stores', 'wear', 'wear mask', 'wear masks', 'wearing', 'wearing mask', 'wearing masks', 'wears', 'wore'] | F28: ['She is taking her son out of school because he has to wear a mask.', 'She refuses to wear a mask.', "It's because they hate wearing masks and our boundaries with covid safety.", "They're always going on about how Covid isn't real so there's no need to wear masks.", "Says he'll wear a mask (I don't fucking believe him) and that they'll disinfect surfaces.", 'About how yes you do need to wear a mask.', 'She refused to wear a mask.', "They don't take the pandemic seriously, to the point where my stepdad refuses to wear masks in public.", "After a while it was clear he just doesn't wear a mask - ever.", 'Do you still have to wear a mask?', 'I received similar conspiracy theories such as "\n\n* Masks make you more sick \n* Masks are just a hoax, they don\'t do anything\n* The virus isn\'t real so why should I have to wear a mask\n* And finally "I\'m not going to be told what to do.', "i've told her that i'd rather wear a mask and have it be ineffective later than not wear one and put myself or other people at risk.", 'She was proud to not wear a mask when she went out.', 'But then, of course, there was the insistence that it was only a flu and that masks muzzle us.', 'I told him that he had to wear a mask.'] | G28: Resistance to Mask-Wearing and COVID-19 Denial | I28: 3-Oon after-Beliefs
A29: 243 | B29: 21148 | C29: 1003 | E29: ['anti semitic', 'antisemitic', 'germany', 'hitler', 'holocaust', 'israel', 'jewish', 'jews', 'nazi', 'nazis', 'semitic'] | F29: ['She began to claim the Jewish people were subjugated to the horrors of the Holocaust because they "turned their back on God".', 'was Jewish, and she had no problem then.', 'when he told me what the holocaust was in 3rd grade, bought me every holocaust book I wanted, and took me to every holocaust museum in the state, now says that \\*maybe\\* 200k Jews died in the holocaust, and "to understand the reason why the nazis did what they did, you have to look at what the Jews did to Europe."', "It's basically the same reasons most Neo-Nazis you'd think about have for having their views: prejudice towards Jews, denying the Holocaust, etc.", 'And it‚Äôs not just Jews.', 'Mind you she is a Latino Jewish Woman and I told her that her entire rhetoric is the same rhetoric the Nazis said about the Jews.', 'The jews had it coming by virtue of the holocaust happening.', "What's worse, they're all about Jews.", 'Trump is a "Jewish shill" to her group.', "She now believes Jewish l people control the government, the media and the media lies and is evil and are trying to hurt good hardworking people (I'm Jewish)\n3."] | G29: Antisemitic Conspiracy Beliefs | I29: 3-Oon after-Beliefs
A30: 247 | B30: 293404 | C30: 145 | E30: ['app', 'channel', 'chat', 'chats', 'german', 'groups', 'messages', 'mocking', 'platforms', 'recommendation', 'telegram', 'tik', 'tik tok', 'tok', 'users', 'using', 'wayfair', 'whatsapp'] | F30: ["Since they took down Velveeta Voldemort's twitter, my mother and her Q friends moved over to telegram.", 'My dad especially, he gets a lot of his news now from Telegram...', 'She also began using Telegram.', "Is Telegram ONLY for Q's?", 'But she knows how to install telegram?', 'Telegram is her big one.', 'Their telegram is constantly advertising trump scams.', "Telegram\n \nThis is where she got most of her 'information'.", 'Eventually she ended up on Telegram.', "He been listening to 'pastors' recently on Telegram."] | G30: Telegram Usage for QAnon Information | I30: 3-Oon after-Behavior/action
A31: 248 | B31: 152348 | C31: 240 | E31: ['ball', 'earth', 'earth flat', 'earther', 'flat', 'flat earth', 'flat earther', 'globe', 'moon', 'prove', 'round', 'space', 'sun'] | F31: ["In fact, she doesn't understand the world spins at all cause she thinks the fucking earth is flat.", 'Yesterday, I found out she was drinking Borax and is convinced the earth is flat.', 'and guess what, flat earth!', 'She brought up ‚ÄúFlat earth theory‚Äú.', 'Then he got into Flat Earth.', 'If you talked about flat earth.', 'Is the earth fucking flat ?', "She's in so deep she believes in flat earth now.", 'I saw something a while back indicating she might start believing the earth is flat.', '* The earth is flat or flat with a dome over it.'] | G31: Flat Earth Belief Among QAnon Followers | I31: 3-Oon after-Beliefs
A32: 249 | B32: 206306 | C32: 203 | E32: ['chem', 'chemtrails', 'climate', 'climate change', 'environmental', 'fires', 'global', 'global warming', 'hoax', 'man made', 'manufactured', 'science', 'scientists', 'sky', 'storm', 'technology', 'warming', 'weather'] | F32: ['Climate change is a lie.', "I'm sorry, but if you can't understand that climate change is real...", 'I corrected her by saying climate change causes extreme weather on both ends.', 'What I have heard is that she no longer believes that climate change is human caused.', 'Climate change is a hoax.', 'And she believes in Climate change.', 'she anticipates the global elite will force us into serfdom and use climate change as an excuse (climate change research is a particular passion of mine).', 'When I try to talk about climate change she accuses me of wanting to ban fracking and says that the US has "one of the strictest guidelines" when it comes to climate change.', "Also, a weird one, suddenly he doesn't believe in climate change when he used too.", 'Climate change is a lie, vaccines were untested, etc.'] | G32: Climate Change Conspiracy Beliefs | I32: 3-Oon after-Beliefs
A33: 253 | B33: 280455 | C33: 144 | E33: ['believe trump', 'believes trump', 'bless', 'could literally', 'donald', 'donald trump', 'jesus', 'messiah', 'prayed', 'savior', 'thinks trump', 'told trump', 'trump god', 'trump like', 'worship', 'worshipping', 'worships'] | F33: ['Trump is his god now.', 'They believe Trump is God sent.', 'He believes Trump is god basically.', 'They began to express their worship of Donald Trump, and how he is "the savior" of the world.', 'Now with our friend, I\'ve had some success in deradicalizing her about "Trump is the messiah."', "She's posted it on Twitter saying all of this and that she is the next messiah.", 'And I don‚Äôt think she thinks Trump is the messiah, or the best president, or any of that.', 'She‚Äôs always been a Trumper and has gotten more and more religious over the years telling me that ‚Äúit‚Äôs a fight of good vs. evil blah blah.‚Äù Now the other day she told me Trump is a false messiah ‚Äúif you read the Bible‚Äù and we need to see through the lies of deception.', 'She thinks trump is the messiah.', "Trump is God's chosen, after all."] | G33: Trump as a Religious Figure | I33: 3-Oon after-Beliefs
A34: 254 | B34: 156419 | C34: 223 | E34: ['compassion', 'compassionate', 'empathetic', 'empathize', 'empathy', 'ever known', 'evident', 'fun', 'generous', 'kindness', 'lack', 'nice', 'person ever', 'sweet', 'sympathy', 'thoughtful', 'understanding', 'used kind', 'woman'] | F34: ['She used to be one of the most compassionate people I know.', 'She‚Äôs not the fun, kind, compassionate woman that I remember growing up.', 'But, with what he says and does I just can‚Äôt have any compassion or empathy for him at this point.', 'love and compassion and empathy for fucking everyone.', 'She used to be the most kind, generous, creative and thoughtful person at her core.', 'She was always so kind and generous and caring and always taught me to be compassionate, open-minded, and think critically, it‚Äôs so wild to see how quickly she dropped all of those qualities.', 'She is the most caring, compassionate person I‚Äôve ever known.', 'He does not show compassion love or empathy and that is my fault he says.', 'He shows nothing about compassion and empathy.', "There's no empathy or anything."] | G34: Loss of Compassion and Empathy in Loved Ones | I34: 3-Oon after-Behavior/action
A35: 259 | B35: 22,37 | C35: 1343 | E35: ['antifa', 'black', 'black lives', 'black people', 'blm', 'capital', 'capitol', 'flag', 'flags', 'insurrection', 'protest', 'protests', 'racism', 'racist', 'riot', 'riots', 'white'] | F35: ['When it first happened, it was ANTIFA.', 'She kept deflecting the conversation with BLM, Antifa, and anyrhing other than the topic at hand.', 'She claimed she had many black friends and wasn‚Äôt racist.', 'Early on he hinted that it might have been Antifa/BLM who entered the Capitol, but I‚Äôm not sure what he thinks now‚Äìand I‚Äôm afraid to ask!', 'The Capitol attack was antifa.', 'So‚Ä¶.Was it Antifa or not?', 'She hasn‚Äôt been speaking much to me lately as I‚Äôm a supporter of BLM and antifa.', 'I do not support ANTIFA under any circumstance.', 'We used to have conversations about politics civilly during the BLM protests and although she was on edge because Trump condemned the protest, she agreed for some time the Black Lives Matter movement was necessary.', 'I asked her if it had to do with BLM?'] | G35: QAnon Conspiracy and Misattribution of Protests | H35: … (BLM and Antifa) | I35: 3-Oon after-Behavior/action
A36: 260 | B36: 65,84 | C36: 658 | E36: ['drag', 'gay', 'gay people', 'homophobic', 'lgbt', 'lgbtq', 'queer', 'trans', 'trans people', 'transgender', 'transphobic'] | F36: ['Her opinions on gay and queer people changed.', 'Then he came out as gay.', "He hates Trans people with a passion but somehow claims he's okay with gay people despite having zero gay or lesbian friends.", 'She used to be cool with gay and trans people.', 'He is also gay apparently.', 'Before she has said that trans people are only trans because of vaccines.', 'More recently, he has been going on rants about trans people and yesterday we had a blow up over a trans issue.', 'yesterday she said that trans people are ruining things for gay people.', 'He has a severe issue with bisexual and trans people (???????)', "She already knows im trans, but she doesn't know about the hormones yet."] | G36: Family Conflicts Over LGBTQ+ Issues | I36: 3-Oon after-Behavior/action
A37: 264 | B37: 247347 | C37: 170 | E37: ['additionally', 'conversion', 'counseling', 'counselor', 'couples', 'depressed', 'depression', 'go therapy', 'mental health', 'need keep', 'refuses', 'seek', 'separately', 'therapist', 'therapists', 'therapy'] | F37: ['We tried couples counseling, individual counseling for him, meditation lawyer but nothing worked.', 'She does see a therapist but they do CBT therapy.', 'Like this man who has been in therapy for fucking years and advocates for marriage counseling and attributes a lot of his own success in dealing with ADHD/Dyslexia to therapy.. is anti therapy.', 'I am in the process of getting into therapy myself, so I will try to use this as leverage for her, as well as seek advice from my therapist on how to proceed.', 'She tried to book a session with the therapist without me until the therapist said that they wouldn‚Äôt do that.', 'She won‚Äôt see the therapist she used to go to, because she knows the therapist is a liberal so she doesn‚Äôt trust her.', 'I‚Äôm planning on asking him to go to marriage counseling with me.', 'As you know, he won‚Äôt consider any kind of counseling because he doesn‚Äôt see it as a problem.', 'She refuses therapy so far bc God is her therapist.', "He won't go to counseling."] | G37: Resistance to Therapy and Counseling | I37: 3-Oon after-Behavior/action
A38: 269 | B38: 12142 | C38: 1392 | E38: ['cult', 'cult like', 'cultists', 'cults', 'deprogramming', 'followers', 'hassan', 'imaginary', 'join', 'joined', 'leader', 'loved ones', 'make seem', 'say sorry', 'shes'] | F38: ['She doesn‚Äôt realize that she‚Äôs in a cult.', 'It‚Äôs a cult, and she doesn‚Äôt see it.', 'So YAY I feel that maybe she is softening on this cult.', "It's like she traded one cult for another.", 'This stupid cult has taken my mother from me.', 'Many have left the cult.', "She doesn't see it as a cult at all.", "I'm basically in a cult and there's nothing I can do about it.", "That's when I realized that he's always been in a cult since I've known him.", 'He got out of the cult.'] | G38: Family Struggles with QAnon Cult Involvement | H38: Perception of QAnon as Cult
A39: 271 | B39: 38112255 | C39: 857 | E39: ['articles', 'bbc', 'cable', 'cnn', 'fox', 'fox news', 'newsmax', 'oan', 'oann', 'podcast', 'podcasts', 'source', 'sources', 'stop listening', 'trying destroy', 'tv', 'watch fox', 'watch fox news', 'watches', 'watching fox', 'watching fox news'] | F39: ['So my dad is someone who always watches Fox News and is always on twitter.', 'My father usually has Fox News going.', 'Posts a fox video on it.', 'Fox News was never on in the house before this.', 'I just know he gets his drivel from Fox News.', 'Always had Fox News on TV.', 'My mom was always into Fox News when I was a kid.', 'Fox News is weaponizing people.', 'Just Fox News until he kicks the bucket.', "My dad's entire worldview comes from Fox News.", 'Fox News is on constantly ‚Äî he won‚Äôt watch anything else.', 'What the hell has Fox News done with my dad?', 'They watch all the conservative news channels like fox news, OAN, newsmax, etc.', 'He‚Äôs never not listening to a dumb podcast or Fox News.', 'He started with Fox News then Newsmax and then a bottomless YouTube rabbit hole.'] | G39: Influence of Conservative Media on Family Dynamics | H39: Fox News Consumption | I39: 2-Trigger-Conservative news
A40: 276 | B40: 24311350 | C40: 906 | E40: ['10 years', '20 years', 'best friend', 'best friends', 'close friend', 'close friends', 'closer', 'enjoyed', 'friends always', 'friends since', 'friendship', 'friendships', 'good friend', 'high school', 'make friends', 'never close', 'one best', 'one best friends', 'really felt', 'ten', 'ten years', 'think lost', 'used close', 'years older'] | F40: ['She was always filthy, and she was my best friend.', 'She used to be my best friend.', 'We are in a friendship of 3 people.', 'I loved our friendship so much.', 'He used to be my best friend.', 'We loved all of the same things and he was truly my best friend.', 'He was my best friend and my first real love.', 'she was my best friend, seriously.', 'Can I save this friendship?', 'He‚Äôs my best friend basically.', 'He was my best friend.', "It's about what to do with the friendship, yes.", 'She‚Äôs always been my best friend.', "I knew there and then our friendship couldn't last.", 'She was my best friend for most of my life.'] | G40: Strained Friendships Due to QAnon Involvement | H40: Oon and narrator relationship - best friend | I40: 0-Background-Relationship with narr
